[{"center_id": 579272, "name": "DH SHIVPURI- SSM School", "state_name": "Madhya Pradesh", "district_name": "Shivpuri", "block_name": "Shivpuri", "pincode": 473551, "lat": 25, "long": 78, "from": "09:00:00", "to": "18:00:00", "fee_type": "Free", "sessions": [{"session_id": "9ab846f6-fa9d-45f8-8ce8-b0a98e1d31cd", "date": "01-05-2021", "available_capacity": 7, "min_age_limit": 45, "vaccine": "", "slots": ["09:00AM-11:00AM", "11:00AM-01:00PM", "01:00PM-03:00PM", "03:00PM-06:00PM"]}]}, {"center_id": 683661, "name": "09 Ward Manglam Shivpuri", "state_name": "Madhya Pradesh", "district_name": "Shivpuri", "block_name": "Shivpuri", "pincode": 473551, "lat": 25, "long": 77, "from": "09:00:00", "to": "18:00:00", "fee_type": "Free", "sessions": [{"session_id": "0a6586a2-e583-4fb8-8ff5-d0c60890c9f5", "date": "01-05-2021", "available_capacity": 1, "min_age_limit": 18, "vaccine": "", "slots": ["09:00AM-11:00AM", "11:00AM-01:00PM", "01:00PM-03:00PM", "03:00PM-06:00PM"]}]}]