[{"center_id": 603429, "name": "Bobbili-CHC-CVC", "state_name": "Andhra Pradesh", "district_name": "Vizianagaram", "block_name": "Bobbili", "pincode": 535558, "lat": 18, "long": 83, "from": "09:00:00", "to": "18:00:00", "fee_type": "Free", "sessions": [{"session_id": "c9e03c75-f985-4fd8-a192-1b4f1b854ce0", "date": "14-05-2021", "available_capacity": 49, "min_age_limit": 45, "vaccine": "", "slots": ["09:00AM-11:00AM", "11:00AM-01:00PM", "01:00PM-03:00PM", "03:00PM-06:00PM"]}, {"session_id": "2e76e2eb-2865-4574-9a89-75ae2e09a10c", "date": "15-05-2021", "available_capacity": 47, "min_age_limit": 45, "vaccine": "", "slots": ["09:00AM-11:00AM", "11:00AM-01:00PM", "01:00PM-03:00PM", "03:00PM-06:00PM"]}, {"session_id": "6182c1c9-66ff-4d8f-9277-24727a8dd903", "date": "17-05-2021", "available_capacity": 49, "min_age_limit": 45, "vaccine": "", "slots": ["09:00AM-11:00AM", "11:00AM-01:00PM", "01:00PM-03:00PM", "03:00PM-06:00PM"]}, {"session_id": "48ea6009-936b-4012-9e4b-c4ec55c1a380", "date": "18-05-2021", "available_capacity": 49, "min_age_limit": 45, "vaccine": "", "slots": ["09:00AM-11:00AM", "11:00AM-01:00PM", "01:00PM-03:00PM", "03:00PM-06:00PM"]}, {"session_id": "273fe352-370b-42d7-a256-b9de6dcc54d1", "date": "19-05-2021", "available_capacity": 46, "min_age_limit": 45, "vaccine": "", "slots": ["09:00AM-11:00AM", "11:00AM-01:00PM", "01:00PM-03:00PM", "03:00PM-06:00PM"]}, {"session_id": "c1bc7636-5f2b-4ff9-aa52-80846526eb0e", "date": "20-05-2021", "available_capacity": 50, "min_age_limit": 45, "vaccine": "", "slots": ["09:00AM-11:00AM", "11:00AM-01:00PM", "01:00PM-03:00PM", "03:00PM-06:00PM"]}]}, {"center_id": 603524, "name": "Bondapalli-PHC-CVC", "state_name": "Andhra Pradesh", "district_name": "Vizianagaram", "block_name": "Bondapalli", "pincode": 535260, "lat": 18, "long": 83, "from": "09:00:00", "to": "18:00:00", "fee_type": "Free", "sessions": [{"session_id": "3eb8ab7b-c200-4a63-92ca-c4a5fd36002a", "date": "14-05-2021", "available_capacity": 46, "min_age_limit": 45, "vaccine": "", "slots": ["09:00AM-11:00AM", "11:00AM-01:00PM", "01:00PM-03:00PM", "03:00PM-06:00PM"]}, {"session_id": "01435a9f-d525-4bba-a3ea-66bf3d73986b", "date": "15-05-2021", "available_capacity": 47, "min_age_limit": 45, "vaccine": "", "slots": ["09:00AM-11:00AM", "11:00AM-01:00PM", "01:00PM-03:00PM", "03:00PM-06:00PM"]}, {"session_id": "469bb036-175e-4094-a338-4d7b589de459", "date": "17-05-2021", "available_capacity": 50, "min_age_limit": 45, "vaccine": "", "slots": ["09:00AM-11:00AM", "11:00AM-01:00PM", "01:00PM-03:00PM", "03:00PM-06:00PM"]}, {"session_id": "cf935b23-3245-46ef-9d20-6837a27843ff", "date": "18-05-2021", "available_capacity": 50, "min_age_limit": 45, "vaccine": "", "slots": ["09:00AM-11:00AM", "11:00AM-01:00PM", "01:00PM-03:00PM", "03:00PM-06:00PM"]}, {"session_id": "b0d0eeaa-7ee9-42ef-b972-911e1a318731", "date": "19-05-2021", "available_capacity": 50, "min_age_limit": 45, "vaccine": "", "slots": ["09:00AM-11:00AM", "11:00AM-01:00PM", "01:00PM-03:00PM", "03:00PM-06:00PM"]}, {"session_id": "a296b9d5-4d5f-4cbc-a765-67723a0ffb28", "date": "20-05-2021", "available_capacity": 50, "min_age_limit": 45, "vaccine": "", "slots": ["09:00AM-11:00AM", "11:00AM-01:00PM", "01:00PM-03:00PM", "03:00PM-06:00PM"]}]}, {"center_id": 608922, "name": "Cheepurupalli - CHC-CVC", "state_name": "Andhra Pradesh", "district_name": "Vizianagaram", "block_name": "Cheepurupalli", "pincode": 535128, "lat": 17, "long": 81, "from": "09:00:00", "to": "18:00:00", "fee_type": "Free", "sessions": [{"session_id": "d40532b6-9f28-476a-81e2-f2bf07fcde7b", "date": "14-05-2021", "available_capacity": 49, "min_age_limit": 45, "vaccine": "", "slots": ["09:00AM-11:00AM", "11:00AM-01:00PM", "01:00PM-03:00PM", "03:00PM-06:00PM"]}, {"session_id": "d8de1d96-6541-4c0f-84cb-12d33f21b3d6", "date": "15-05-2021", "available_capacity": 50, "min_age_limit": 45, "vaccine": "", "slots": ["09:00AM-11:00AM", "11:00AM-01:00PM", "01:00PM-03:00PM", "03:00PM-06:00PM"]}, {"session_id": "86aa836f-03a9-416c-8f40-6693238287b6", "date": "17-05-2021", "available_capacity": 49, "min_age_limit": 45, "vaccine": "", "slots": ["09:00AM-11:00AM", "11:00AM-01:00PM", "01:00PM-03:00PM", "03:00PM-06:00PM"]}, {"session_id": "40a5b179-6dc7-43fd-bfce-2e7009fd2067", "date": "18-05-2021", "available_capacity": 50, "min_age_limit": 45, "vaccine": "", "slots": ["09:00AM-11:00AM", "11:00AM-01:00PM", "01:00PM-03:00PM", "03:00PM-06:00PM"]}, {"session_id": "100806be-9343-4f27-bc81-a3a5b4aff963", "date": "19-05-2021", "available_capacity": 49, "min_age_limit": 45, "vaccine": "", "slots": ["09:00AM-11:00AM", "11:00AM-01:00PM", "01:00PM-03:00PM", "03:00PM-06:00PM"]}, {"session_id": "603f6a27-bcab-4259-bc70-40334911d2ec", "date": "20-05-2021", "available_capacity": 48, "min_age_limit": 45, "vaccine": "", "slots": ["09:00AM-11:00AM", "11:00AM-01:00PM", "01:00PM-03:00PM", "03:00PM-06:00PM"]}]}, {"center_id": 599930, "name": "Dattirajeru - PHC-CVC", "state_name": "Andhra Pradesh", "district_name": "Vizianagaram", "block_name": "Dathirajeru", "pincode": 535580, "lat": 18, "long": 83, "from": "09:00:00", "to": "18:00:00", "fee_type": "Free", "sessions": [{"session_id": "4dbc35b7-1695-4cbb-98bf-abc0f97704ac", "date": "14-05-2021", "available_capacity": 50, "min_age_limit": 45, "vaccine": "", "slots": ["09:00AM-11:00AM", "11:00AM-01:00PM", "01:00PM-03:00PM", "03:00PM-06:00PM"]}, {"session_id": "29e4c095-7997-4f34-9539-33d2929cb5b8", "date": "15-05-2021", "available_capacity": 50, "min_age_limit": 45, "vaccine": "", "slots": ["09:00AM-11:00AM", "11:00AM-01:00PM", "01:00PM-03:00PM", "03:00PM-06:00PM"]}, {"session_id": "76466bf8-f8f1-4288-a427-a01124cb6b11", "date": "17-05-2021", "available_capacity": 50, "min_age_limit": 45, "vaccine": "", "slots": ["09:00AM-11:00AM", "11:00AM-01:00PM", "01:00PM-03:00PM", "03:00PM-06:00PM"]}, {"session_id": "759c5a3d-7059-42e6-9ed3-c91f8fdc15f1", "date": "18-05-2021", "available_capacity": 50, "min_age_limit": 45, "vaccine": "", "slots": ["09:00AM-11:00AM", "11:00AM-01:00PM", "01:00PM-03:00PM", "03:00PM-06:00PM"]}, {"session_id": "6dfaeaea-70d1-4ce2-a0ad-b4d3efaec037", "date": "19-05-2021", "available_capacity": 50, "min_age_limit": 45, "vaccine": "", "slots": ["09:00AM-11:00AM", "11:00AM-01:00PM", "01:00PM-03:00PM", "03:00PM-06:00PM"]}, {"session_id": "6b1999a1-d44a-4b45-b8ed-5457b1f36a99", "date": "20-05-2021", "available_capacity": 50, "min_age_limit": 45, "vaccine": "", "slots": ["09:00AM-11:00AM", "11:00AM-01:00PM", "01:00PM-03:00PM", "03:00PM-06:00PM"]}]}, {"center_id": 599785, "name": "Gantyada-PHC-CVC", "state_name": "Andhra Pradesh", "district_name": "Vizianagaram", "block_name": "Gantyada", "pincode": 535215, "lat": 18, "long": 83, "from": "09:00:00", "to": "18:00:00", "fee_type": "Free", "sessions": [{"session_id": "a6a95482-5beb-4d7f-a757-2e15f149fc46", "date": "14-05-2021", "available_capacity": 47, "min_age_limit": 45, "vaccine": "", "slots": ["09:00AM-11:00AM", "11:00AM-01:00PM", "01:00PM-03:00PM", "03:00PM-06:00PM"]}, {"session_id": "2e0b3a4a-d4b4-4265-87db-cf12a62235a1", "date": "15-05-2021", "available_capacity": 49, "min_age_limit": 45, "vaccine": "", "slots": ["09:00AM-11:00AM", "11:00AM-01:00PM", "01:00PM-03:00PM", "03:00PM-06:00PM"]}, {"session_id": "f57445b6-d3aa-4379-8976-4133f3294b26", "date": "17-05-2021", "available_capacity": 50, "min_age_limit": 45, "vaccine": "", "slots": ["09:00AM-11:00AM", "11:00AM-01:00PM", "01:00PM-03:00PM", "03:00PM-06:00PM"]}, {"session_id": "a3e3420b-6280-4e83-94da-e45e136f4f1a", "date": "18-05-2021", "available_capacity": 50, "min_age_limit": 45, "vaccine": "", "slots": ["09:00AM-11:00AM", "11:00AM-01:00PM", "01:00PM-03:00PM", "03:00PM-06:00PM"]}, {"session_id": "cdb1741c-d54d-420b-9524-2ca295108c0a", "date": "19-05-2021", "available_capacity": 48, "min_age_limit": 45, "vaccine": "", "slots": ["09:00AM-11:00AM", "11:00AM-01:00PM", "01:00PM-03:00PM", "03:00PM-06:00PM"]}, {"session_id": "49f515a4-170d-4ae7-9fda-3cd7301d0c83", "date": "20-05-2021", "available_capacity": 50, "min_age_limit": 45, "vaccine": "", "slots": ["09:00AM-11:00AM", "11:00AM-01:00PM", "01:00PM-03:00PM", "03:00PM-06:00PM"]}]}, {"center_id": 603548, "name": "Denkada-PHC-CVC", "state_name": "Andhra Pradesh", "district_name": "Vizianagaram", "block_name": "Denkada", "pincode": 535006, "lat": 18, "long": 83, "from": "09:00:00", "to": "18:00:00", "fee_type": "Free", "sessions": [{"session_id": "7ccb1371-144b-40cc-ad86-15b0ef29c711", "date": "14-05-2021", "available_capacity": 50, "min_age_limit": 45, "vaccine": "", "slots": ["09:00AM-11:00AM", "11:00AM-01:00PM", "01:00PM-03:00PM", "03:00PM-06:00PM"]}, {"session_id": "adfc422f-06ca-4d7e-abdb-816392b7ebad", "date": "15-05-2021", "available_capacity": 48, "min_age_limit": 45, "vaccine": "", "slots": ["09:00AM-11:00AM", "11:00AM-01:00PM", "01:00PM-03:00PM", "03:00PM-06:00PM"]}, {"session_id": "26a4b842-fcc4-4b04-9533-76a534c451c8", "date": "17-05-2021", "available_capacity": 48, "min_age_limit": 45, "vaccine": "", "slots": ["09:00AM-11:00AM", "11:00AM-01:00PM", "01:00PM-03:00PM", "03:00PM-06:00PM"]}, {"session_id": "2591bfbf-d496-4b67-a583-ada08d58618f", "date": "18-05-2021", "available_capacity": 50, "min_age_limit": 45, "vaccine": "", "slots": ["09:00AM-11:00AM", "11:00AM-01:00PM", "01:00PM-03:00PM", "03:00PM-06:00PM"]}, {"session_id": "901d1638-1581-4e99-be50-c089f21bf358", "date": "19-05-2021", "available_capacity": 50, "min_age_limit": 45, "vaccine": "", "slots": ["09:00AM-11:00AM", "11:00AM-01:00PM", "01:00PM-03:00PM", "03:00PM-06:00PM"]}, {"session_id": "c132b8c5-cf50-4c6e-9b8c-dbb14411e2cc", "date": "20-05-2021", "available_capacity": 49, "min_age_limit": 45, "vaccine": "", "slots": ["09:00AM-11:00AM", "11:00AM-01:00PM", "01:00PM-03:00PM", "03:00PM-06:00PM"]}]}, {"center_id": 599815, "name": "Garividi-PHC-CVC", "state_name": "Andhra Pradesh", "district_name": "Vizianagaram", "block_name": "Garividi", "pincode": 535101, "lat": 18, "long": 83, "from": "09:00:00", "to": "18:00:00", "fee_type": "Free", "sessions": [{"session_id": "14524917-0713-4dcf-9bb5-6ddd28216460", "date": "14-05-2021", "available_capacity": 20, "min_age_limit": 45, "vaccine": "", "slots": ["09:00AM-11:00AM", "11:00AM-01:00PM", "01:00PM-03:00PM", "03:00PM-06:00PM"]}, {"session_id": "7ef995b6-c027-475b-b9b8-adfcf007ff0c", "date": "15-05-2021", "available_capacity": 20, "min_age_limit": 45, "vaccine": "", "slots": ["09:00AM-11:00AM", "11:00AM-01:00PM", "01:00PM-03:00PM", "03:00PM-06:00PM"]}, {"session_id": "76711da7-cbdc-40a3-9f87-f605489bd11f", "date": "17-05-2021", "available_capacity": 20, "min_age_limit": 45, "vaccine": "", "slots": ["09:00AM-11:00AM", "11:00AM-01:00PM", "01:00PM-03:00PM", "03:00PM-06:00PM"]}, {"session_id": "14e74141-13ce-4f09-899a-63441a2411b6", "date": "18-05-2021", "available_capacity": 20, "min_age_limit": 45, "vaccine": "", "slots": ["09:00AM-11:00AM", "11:00AM-01:00PM", "01:00PM-03:00PM", "03:00PM-06:00PM"]}, {"session_id": "aac962d8-0ac3-40ef-b654-7145f9402900", "date": "19-05-2021", "available_capacity": 20, "min_age_limit": 45, "vaccine": "", "slots": ["09:00AM-11:00AM", "11:00AM-01:00PM", "01:00PM-03:00PM", "03:00PM-06:00PM"]}]}, {"center_id": 608933, "name": "Gajapathinagaram-CHC-CVC", "state_name": "Andhra Pradesh", "district_name": "Vizianagaram", "block_name": "Gajapathinagaram", "pincode": 535270, "lat": 18, "long": 81, "from": "09:00:00", "to": "18:00:00", "fee_type": "Free", "sessions": [{"session_id": "28862803-768d-4e1b-b609-12b696d454ca", "date": "14-05-2021", "available_capacity": 49, "min_age_limit": 45, "vaccine": "", "slots": ["09:00AM-11:00AM", "11:00AM-01:00PM", "01:00PM-03:00PM", "03:00PM-06:00PM"]}, {"session_id": "f75e311a-e112-4526-9eac-b5efbd267a69", "date": "15-05-2021", "available_capacity": 50, "min_age_limit": 45, "vaccine": "", "slots": ["09:00AM-11:00AM", "11:00AM-01:00PM", "01:00PM-03:00PM", "03:00PM-06:00PM"]}, {"session_id": "82c0e35f-fc0e-4322-a056-d779b111b2df", "date": "17-05-2021", "available_capacity": 48, "min_age_limit": 45, "vaccine": "", "slots": ["09:00AM-11:00AM", "11:00AM-01:00PM", "01:00PM-03:00PM", "03:00PM-06:00PM"]}, {"session_id": "33617b37-4cfb-4005-91ff-22a30da828c3", "date": "18-05-2021", "available_capacity": 50, "min_age_limit": 45, "vaccine": "", "slots": ["09:00AM-11:00AM", "11:00AM-01:00PM", "01:00PM-03:00PM", "03:00PM-06:00PM"]}, {"session_id": "a1c4bfdc-34f9-42d4-8ec9-481314d83e36", "date": "19-05-2021", "available_capacity": 48, "min_age_limit": 45, "vaccine": "", "slots": ["09:00AM-11:00AM", "11:00AM-01:00PM", "01:00PM-03:00PM", "03:00PM-06:00PM"]}, {"session_id": "29e198a9-3b11-45b0-b585-3d8ddf9e4194", "date": "20-05-2021", "available_capacity": 50, "min_age_limit": 45, "vaccine": "", "slots": ["09:00AM-11:00AM", "11:00AM-01:00PM", "01:00PM-03:00PM", "03:00PM-06:00PM"]}]}, {"center_id": 599614, "name": "Bhadragiri -CHC-CVC", "state_name": "Andhra Pradesh", "district_name": "Vizianagaram", "block_name": "GL Puram", "pincode": 535523, "lat": 18, "long": 83, "from": "09:00:00", "to": "18:00:00", "fee_type": "Free", "sessions": [{"session_id": "1a7c05c4-9522-4b34-beb0-eead0de85dfe", "date": "14-05-2021", "available_capacity": 50, "min_age_limit": 45, "vaccine": "", "slots": ["09:00AM-11:00AM", "11:00AM-01:00PM", "01:00PM-03:00PM", "03:00PM-06:00PM"]}, {"session_id": "c19b0066-f4bf-4d12-b33a-5a7dfc6d67d3", "date": "15-05-2021", "available_capacity": 50, "min_age_limit": 45, "vaccine": "", "slots": ["09:00AM-11:00AM", "11:00AM-01:00PM", "01:00PM-03:00PM", "03:00PM-06:00PM"]}, {"session_id": "c28cf43c-23f7-4f6e-9725-5d3df3185da2", "date": "17-05-2021", "available_capacity": 50, "min_age_limit": 45, "vaccine": "", "slots": ["09:00AM-11:00AM", "11:00AM-01:00PM", "01:00PM-03:00PM", "03:00PM-06:00PM"]}, {"session_id": "ef476020-97e2-414e-bb2d-f8bca7fe083b", "date": "18-05-2021", "available_capacity": 50, "min_age_limit": 45, "vaccine": "", "slots": ["09:00AM-11:00AM", "11:00AM-01:00PM", "01:00PM-03:00PM", "03:00PM-06:00PM"]}, {"session_id": "bff73a34-b13b-4d2e-9c23-a005759ea3bf", "date": "19-05-2021", "available_capacity": 50, "min_age_limit": 45, "vaccine": "", "slots": ["09:00AM-11:00AM", "11:00AM-01:00PM", "01:00PM-03:00PM", "03:00PM-06:00PM"]}, {"session_id": "a4b0e162-2bf1-417d-8d3b-d830ea4bb50c", "date": "20-05-2021", "available_capacity": 50, "min_age_limit": 45, "vaccine": "", "slots": ["09:00AM-11:00AM", "11:00AM-01:00PM", "01:00PM-03:00PM", "03:00PM-06:00PM"]}]}, {"center_id": 600044, "name": "Ramabhadrapuram-PHC-CVC", "state_name": "Andhra Pradesh", "district_name": "Vizianagaram", "block_name": "RB Puram", "pincode": 535579, "lat": 0, "long": 0, "from": "09:00:00", "to": "18:00:00", "fee_type": "Free", "sessions": [{"session_id": "06cea596-6326-4eb3-b3be-67b97bec9e8d", "date": "18-05-2021", "available_capacity": 33, "min_age_limit": 45, "vaccine": "", "slots": ["09:00AM-11:00AM", "11:00AM-01:00PM", "01:00PM-03:00PM", "03:00PM-06:00PM"]}]}]