[{"center_id": 571462, "name": "Kalapipal Block Hospital", "state_name": "Madhya Pradesh", "district_name": "Shajapur", "block_name": "KALAPIPAL", "pincode": 465337, "lat": 23, "long": 76, "from": "09:00:00", "to": "18:00:00", "fee_type": "Free", "sessions": [{"session_id": "d4afc323-12e2-4c1a-8e0e-f2a38a1cdbe9", "date": "30-04-2021", "available_capacity": 9, "min_age_limit": 45, "vaccine": "", "slots": ["09:00AM-11:00AM", "11:00AM-01:00PM", "01:00PM-03:00PM", "03:00PM-06:00PM"]}, {"session_id": "c2ba3716-acf1-4cf3-ab4d-7fdac00e5c08", "date": "01-05-2021", "available_capacity": 10, "min_age_limit": 45, "vaccine": "", "slots": ["09:00AM-11:00AM", "11:00AM-01:00PM", "01:00PM-03:00PM", "03:00PM-06:00PM"]}, {"session_id": "8f18113b-d3c2-4528-a3dd-30f37e0ffc34", "date": "03-05-2021", "available_capacity": 15, "min_age_limit": 45, "vaccine": "", "slots": ["09:00AM-11:00AM", "11:00AM-01:00PM", "01:00PM-03:00PM", "03:00PM-06:00PM"]}, {"session_id": "9e1b74cd-f3ff-40a5-a9ab-58a4c5efbda3", "date": "04-05-2021", "available_capacity": 20, "min_age_limit": 45, "vaccine": "", "slots": ["09:00AM-11:00AM", "11:00AM-01:00PM", "01:00PM-03:00PM", "03:00PM-06:00PM"]}, {"session_id": "990086f0-cf7b-49bf-887a-f44ee30947f9", "date": "05-05-2021", "available_capacity": 14, "min_age_limit": 45, "vaccine": "", "slots": ["09:00AM-11:00AM", "11:00AM-01:00PM", "01:00PM-03:00PM", "03:00PM-06:00PM"]}]}, {"center_id": 586647, "name": "Shajapur DHS Hall", "state_name": "Madhya Pradesh", "district_name": "Shajapur", "block_name": "SHAJAPUR", "pincode": 465001, "lat": 23, "long": 76, "from": "09:00:00", "to": "18:00:00", "fee_type": "Free", "sessions": [{"session_id": "8c76f2ce-a616-4a5e-9ce7-025bf3625489", "date": "30-04-2021", "available_capacity": 35, "min_age_limit": 45, "vaccine": "", "slots": ["09:00AM-11:00AM", "11:00AM-01:00PM", "01:00PM-03:00PM", "03:00PM-06:00PM"]}, {"session_id": "c269bbb5-7f54-47d5-9dd8-cec9b6bebdea", "date": "06-05-2021", "available_capacity": 48, "min_age_limit": 45, "vaccine": "", "slots": ["09:00AM-11:00AM", "11:00AM-01:00PM", "01:00PM-03:00PM", "03:00PM-06:00PM"]}]}, {"center_id": 574205, "name": "Sundarshi Ccp", "state_name": "Madhya Pradesh", "district_name": "Shajapur", "block_name": "SHAJAPUR", "pincode": 465113, "lat": 23, "long": 76, "from": "09:00:00", "to": "18:00:00", "fee_type": "Free", "sessions": [{"session_id": "3f4a0943-595d-44ef-8a7d-87b78af92ac4", "date": "30-04-2021", "available_capacity": 10, "min_age_limit": 45, "vaccine": "", "slots": ["09:00AM-11:00AM", "11:00AM-01:00PM", "01:00PM-03:00PM", "03:00PM-06:00PM"]}, {"session_id": "fffd88a5-5d48-4c98-bf38-73793bbd7abf", "date": "03-05-2021", "available_capacity": 10, "min_age_limit": 45, "vaccine": "", "slots": ["09:00AM-11:00AM", "11:00AM-01:00PM", "01:00PM-03:00PM", "03:00PM-06:00PM"]}, {"session_id": "f851eebb-5869-4757-b725-3debe83f4b9e", "date": "06-05-2021", "available_capacity": 10, "min_age_limit": 45, "vaccine": "", "slots": ["09:00AM-11:00AM", "11:00AM-01:00PM", "01:00PM-03:00PM", "03:00PM-06:00PM"]}]}, {"center_id": 655462, "name": "Kewda Khedi SHC", "state_name": "Madhya Pradesh", "district_name": "Shajapur", "block_name": "Moman Badodiya", "pincode": 465223, "lat": 23, "long": 76, "from": "09:00:00", "to": "18:00:00", "fee_type": "Free", "sessions": [{"session_id": "6b7f535c-2168-4d71-b97e-e7e9b8555110", "date": "01-05-2021", "available_capacity": 10, "min_age_limit": 45, "vaccine": "", "slots": ["09:00AM-11:00AM", "11:00AM-01:00PM", "01:00PM-03:00PM", "03:00PM-06:00PM"]}, {"session_id": "2c577d9f-f7db-4351-9e73-e7dba6e964e1", "date": "03-05-2021", "available_capacity": 10, "min_age_limit": 45, "vaccine": "", "slots": ["09:00AM-11:00AM", "11:00AM-01:00PM", "01:00PM-03:00PM", "03:00PM-06:00PM"]}]}, {"center_id": 571428, "name": "Polaikala CCP", "state_name": "Madhya Pradesh", "district_name": "Shajapur", "block_name": "SHUJALPUR", "pincode": 465116, "lat": 23, "long": 76, "from": "09:00:00", "to": "18:00:00", "fee_type": "Free", "sessions": [{"session_id": "6e621cdb-4527-4c4f-a879-1dd27c4b318c", "date": "01-05-2021", "available_capacity": 8, "min_age_limit": 45, "vaccine": "", "slots": ["09:00AM-11:00AM", "11:00AM-01:00PM", "01:00PM-03:00PM", "03:00PM-06:00PM"]}, {"session_id": "ac1e2567-9caa-4c74-8f8e-18485ab43514", "date": "03-05-2021", "available_capacity": 19, "min_age_limit": 45, "vaccine": "", "slots": ["09:00AM-11:00AM", "11:00AM-01:00PM", "01:00PM-03:00PM", "03:00PM-06:00PM"]}, {"session_id": "527bd0a1-150d-4f27-9e73-274191b9e68a", "date": "04-05-2021", "available_capacity": 10, "min_age_limit": 45, "vaccine": "", "slots": ["09:00AM-11:00AM", "11:00AM-01:00PM", "01:00PM-03:00PM", "03:00PM-06:00PM"]}]}, {"center_id": 595589, "name": "Sujalpur Mandi Hospital 45", "state_name": "Madhya Pradesh", "district_name": "Shajapur", "block_name": "SHUJALPUR", "pincode": 465333, "lat": 23, "long": 76, "from": "09:00:00", "to": "18:00:00", "fee_type": "Free", "sessions": [{"session_id": "97caf9bc-d29b-4056-a462-355b61186283", "date": "01-05-2021", "available_capacity": 17, "min_age_limit": 45, "vaccine": "", "slots": ["09:00AM-11:00AM", "11:00AM-01:00PM", "01:00PM-03:00PM", "03:00PM-06:00PM"]}]}, {"center_id": 655481, "name": "Tingazpur SHC", "state_name": "Madhya Pradesh", "district_name": "Shajapur", "block_name": "Moman Badodiya", "pincode": 465227, "lat": 23, "long": 76, "from": "09:00:00", "to": "18:00:00", "fee_type": "Free", "sessions": [{"session_id": "92d2cca9-5ce4-4c3b-9a3d-b17c73405bf2", "date": "01-05-2021", "available_capacity": 10, "min_age_limit": 45, "vaccine": "", "slots": ["09:00AM-11:00AM", "11:00AM-01:00PM", "01:00PM-03:00PM", "03:00PM-06:00PM"]}]}, {"center_id": 655387, "name": "Manglaz SHC", "state_name": "Madhya Pradesh", "district_name": "Shajapur", "block_name": "Moman Badodiya", "pincode": 465227, "lat": 23, "long": 76, "from": "09:00:00", "to": "18:00:00", "fee_type": "Free", "sessions": [{"session_id": "b1506e59-5207-4edb-b4e3-6af7a518bae0", "date": "01-05-2021", "available_capacity": 8, "min_age_limit": 45, "vaccine": "", "slots": ["09:00AM-11:00AM", "11:00AM-01:00PM", "01:00PM-03:00PM", "03:00PM-06:00PM"]}, {"session_id": "a0268e3e-ebd6-49d2-b214-82a2f4a18b5b", "date": "03-05-2021", "available_capacity": 10, "min_age_limit": 45, "vaccine": "", "slots": ["09:00AM-11:00AM", "11:00AM-01:00PM", "01:00PM-03:00PM", "03:00PM-06:00PM"]}]}, {"center_id": 655438, "name": "Kiloda SHC", "state_name": "Madhya Pradesh", "district_name": "Shajapur", "block_name": "Moman Badodiya", "pincode": 465227, "lat": 23, "long": 76, "from": "09:00:00", "to": "18:00:00", "fee_type": "Free", "sessions": [{"session_id": "89816942-6c8d-4ecb-b314-437e3da7cf07", "date": "01-05-2021", "available_capacity": 6, "min_age_limit": 45, "vaccine": "", "slots": ["09:00AM-11:00AM", "11:00AM-01:00PM", "01:00PM-03:00PM", "03:00PM-06:00PM"]}]}, {"center_id": 655395, "name": "Bhaishrod SHC", "state_name": "Madhya Pradesh", "district_name": "Shajapur", "block_name": "Moman Badodiya", "pincode": 465223, "lat": 23, "long": 76, "from": "09:00:00", "to": "18:00:00", "fee_type": "Free", "sessions": [{"session_id": "ddde5295-6ede-42ef-b027-588e741722f2", "date": "01-05-2021", "available_capacity": 9, "min_age_limit": 45, "vaccine": "", "slots": ["09:00AM-11:00AM", "11:00AM-01:00PM", "01:00PM-03:00PM", "03:00PM-06:00PM"]}, {"session_id": "bfda4fa7-2657-4cde-8df7-96a0397f8ff9", "date": "03-05-2021", "available_capacity": 10, "min_age_limit": 45, "vaccine": "", "slots": ["09:00AM-11:00AM", "11:00AM-01:00PM", "01:00PM-03:00PM", "03:00PM-06:00PM"]}]}, {"center_id": 691658, "name": "Excellence School Site 45", "state_name": "Madhya Pradesh", "district_name": "Shajapur", "block_name": "SHAJAPUR", "pincode": 465001, "lat": 0, "long": 0, "from": "09:00:00", "to": "18:00:00", "fee_type": "Free", "sessions": [{"session_id": "2d9dda5b-bc97-423b-8a35-f3b2c6f2b087", "date": "01-05-2021", "available_capacity": 60, "min_age_limit": 45, "vaccine": "", "slots": ["09:00AM-11:00AM", "11:00AM-01:00PM", "01:00PM-03:00PM", "03:00PM-06:00PM"]}]}, {"center_id": 655473, "name": "Borsali SHC", "state_name": "Madhya Pradesh", "district_name": "Shajapur", "block_name": "Moman Badodiya", "pincode": 465223, "lat": 23, "long": 76, "from": "09:00:00", "to": "18:00:00", "fee_type": "Free", "sessions": [{"session_id": "a4478106-994c-47d4-be54-f7aa66bfacf5", "date": "01-05-2021", "available_capacity": 10, "min_age_limit": 45, "vaccine": "", "slots": ["09:00AM-11:00AM", "11:00AM-01:00PM", "01:00PM-03:00PM", "03:00PM-06:00PM"]}]}, {"center_id": 574513, "name": "Khokhrakala CCP", "state_name": "Madhya Pradesh", "district_name": "Shajapur", "block_name": "KALAPIPAL", "pincode": 465339, "lat": 23, "long": 76, "from": "09:00:00", "to": "18:00:00", "fee_type": "Free", "sessions": [{"session_id": "fef8d821-d0a4-4351-951e-dff393b8d3e3", "date": "01-05-2021", "available_capacity": 9, "min_age_limit": 45, "vaccine": "", "slots": ["09:00AM-11:00AM", "11:00AM-01:00PM", "01:00PM-03:00PM", "03:00PM-06:00PM"]}, {"session_id": "7cce8092-ce22-4651-a3af-ba43de7ef29a", "date": "03-05-2021", "available_capacity": 9, "min_age_limit": 45, "vaccine": "", "slots": ["09:00AM-11:00AM", "11:00AM-01:00PM", "01:00PM-03:00PM", "03:00PM-06:00PM"]}]}, {"center_id": 574496, "name": "Arniyakala CCP", "state_name": "Madhya Pradesh", "district_name": "Shajapur", "block_name": "KALAPIPAL", "pincode": 465333, "lat": 23, "long": 76, "from": "09:00:00", "to": "18:00:00", "fee_type": "Free", "sessions": [{"session_id": "82f54d8c-e9d8-469d-8dde-89287535425b", "date": "01-05-2021", "available_capacity": 4, "min_age_limit": 45, "vaccine": "", "slots": ["09:00AM-11:00AM", "11:00AM-01:00PM", "01:00PM-03:00PM", "03:00PM-06:00PM"]}, {"session_id": "ff153c27-94b3-4fda-8100-7e68f561a9e1", "date": "03-05-2021", "available_capacity": 20, "min_age_limit": 45, "vaccine": "", "slots": ["09:00AM-11:00AM", "11:00AM-01:00PM", "01:00PM-03:00PM", "03:00PM-06:00PM"]}, {"session_id": "ca09bb6c-307f-4829-aa5a-cb018b746692", "date": "05-05-2021", "available_capacity": 9, "min_age_limit": 45, "vaccine": "", "slots": ["09:00AM-11:00AM", "11:00AM-01:00PM", "01:00PM-03:00PM", "03:00PM-06:00PM"]}]}, {"center_id": 561324, "name": "Bercha Block", "state_name": "Madhya Pradesh", "district_name": "Shajapur", "block_name": "SHAJAPUR", "pincode": 465110, "lat": 23, "long": 76, "from": "09:00:00", "to": "18:00:00", "fee_type": "Free", "sessions": [{"session_id": "4e4d415a-d41c-4482-aca5-aabf11e11a2f", "date": "01-05-2021", "available_capacity": 10, "min_age_limit": 45, "vaccine": "", "slots": ["09:00AM-11:00AM", "11:00AM-01:00PM", "01:00PM-03:00PM", "03:00PM-06:00PM"]}, {"session_id": "9ae2d477-6da3-4016-8467-2cddfa3ecc10", "date": "03-05-2021", "available_capacity": 18, "min_age_limit": 45, "vaccine": "", "slots": ["09:00AM-11:00AM", "11:00AM-01:00PM", "01:00PM-03:00PM", "03:00PM-06:00PM"]}, {"session_id": "b6928d68-f295-4abf-b381-07c3f71cc196", "date": "05-05-2021", "available_capacity": 18, "min_age_limit": 45, "vaccine": "", "slots": ["09:00AM-11:00AM", "11:00AM-01:00PM", "01:00PM-03:00PM", "03:00PM-06:00PM"]}, {"session_id": "5fa65c1f-8d96-4e37-8850-11db7a792527", "date": "06-05-2021", "available_capacity": 20, "min_age_limit": 45, "vaccine": "", "slots": ["09:00AM-11:00AM", "11:00AM-01:00PM", "01:00PM-03:00PM", "03:00PM-06:00PM"]}]}, {"center_id": 691690, "name": "Excellence School Mandi 45", "state_name": "Madhya Pradesh", "district_name": "Shajapur", "block_name": "SHUJALPUR", "pincode": 465333, "lat": 0, "long": 0, "from": "09:00:00", "to": "18:00:00", "fee_type": "Free", "sessions": [{"session_id": "08a41767-9104-42b8-ace4-cc0dc85b943d", "date": "01-05-2021", "available_capacity": 3, "min_age_limit": 45, "vaccine": "", "slots": ["09:00AM-11:00AM", "11:00AM-01:00PM", "01:00PM-03:00PM", "03:00PM-06:00PM"]}]}, {"center_id": 574400, "name": "Bolai PHC CCP", "state_name": "Madhya Pradesh", "district_name": "Shajapur", "block_name": "Moman Badodiya", "pincode": 465220, "lat": 23, "long": 76, "from": "09:00:00", "to": "18:00:00", "fee_type": "Free", "sessions": [{"session_id": "ae2e061d-d9cd-480c-a4f6-262adf96d883", "date": "01-05-2021", "available_capacity": 10, "min_age_limit": 45, "vaccine": "", "slots": ["09:00AM-11:00AM", "11:00AM-01:00PM", "01:00PM-03:00PM", "03:00PM-06:00PM"]}, {"session_id": "c12e4d31-69c7-4f19-be44-f7cdf9cd8b5e", "date": "03-05-2021", "available_capacity": 9, "min_age_limit": 45, "vaccine": "", "slots": ["09:00AM-11:00AM", "11:00AM-01:00PM", "01:00PM-03:00PM", "03:00PM-06:00PM"]}]}, {"center_id": 574408, "name": "Gulana PHC CCP", "state_name": "Madhya Pradesh", "district_name": "Shajapur", "block_name": "Moman Badodiya", "pincode": 465220, "lat": 23, "long": 76, "from": "09:00:00", "to": "18:00:00", "fee_type": "Free", "sessions": [{"session_id": "c10c698f-625b-4d52-981c-b08e3741b6ba", "date": "01-05-2021", "available_capacity": 9, "min_age_limit": 45, "vaccine": "", "slots": ["09:00AM-11:00AM", "11:00AM-01:00PM", "01:00PM-03:00PM", "03:00PM-06:00PM"]}, {"session_id": "e264803a-5e56-45cc-932b-880f5f9a8c29", "date": "03-05-2021", "available_capacity": 8, "min_age_limit": 45, "vaccine": "", "slots": ["09:00AM-11:00AM", "11:00AM-01:00PM", "01:00PM-03:00PM", "03:00PM-06:00PM"]}, {"session_id": "0287b011-5e20-482c-b72f-7a7c896c5f83", "date": "05-05-2021", "available_capacity": 10, "min_age_limit": 45, "vaccine": "", "slots": ["09:00AM-11:00AM", "11:00AM-01:00PM", "01:00PM-03:00PM", "03:00PM-06:00PM"]}, {"session_id": "5e3acdee-553f-4770-a5b5-db584745ced3", "date": "06-05-2021", "available_capacity": 10, "min_age_limit": 45, "vaccine": "", "slots": ["09:00AM-11:00AM", "11:00AM-01:00PM", "01:00PM-03:00PM", "03:00PM-06:00PM"]}]}, {"center_id": 655448, "name": "Noulay SHC", "state_name": "Madhya Pradesh", "district_name": "Shajapur", "block_name": "Moman Badodiya", "pincode": 465227, "lat": 23, "long": 76, "from": "09:00:00", "to": "18:00:00", "fee_type": "Free", "sessions": [{"session_id": "d9117deb-fd0c-475b-94b4-26bcabd561cf", "date": "01-05-2021", "available_capacity": 10, "min_age_limit": 45, "vaccine": "", "slots": ["09:00AM-11:00AM", "11:00AM-01:00PM", "01:00PM-03:00PM", "03:00PM-06:00PM"]}, {"session_id": "7d69715d-2acd-4a75-baf7-1db5d074887b", "date": "03-05-2021", "available_capacity": 10, "min_age_limit": 45, "vaccine": "", "slots": ["09:00AM-11:00AM", "11:00AM-01:00PM", "01:00PM-03:00PM", "03:00PM-06:00PM"]}]}, {"center_id": 620094, "name": "Salsalai SHC", "state_name": "Madhya Pradesh", "district_name": "Shajapur", "block_name": "Moman Badodiya", "pincode": 465227, "lat": 23, "long": 76, "from": "09:00:00", "to": "18:00:00", "fee_type": "Free", "sessions": [{"session_id": "dd68a66a-4501-4d7d-8ca0-3ea9746184e6", "date": "01-05-2021", "available_capacity": 9, "min_age_limit": 45, "vaccine": "", "slots": ["09:00AM-11:00AM", "11:00AM-01:00PM", "01:00PM-03:00PM", "03:00PM-06:00PM"]}, {"session_id": "26ac8c40-410c-4a73-9424-21c3c76f1916", "date": "03-05-2021", "available_capacity": 9, "min_age_limit": 45, "vaccine": "", "slots": ["09:00AM-11:00AM", "11:00AM-01:00PM", "01:00PM-03:00PM", "03:00PM-06:00PM"]}]}, {"center_id": 621831, "name": "Nandani SHC CHO", "state_name": "Madhya Pradesh", "district_name": "Shajapur", "block_name": "KALAPIPAL", "pincode": 465337, "lat": 23, "long": 76, "from": "09:00:00", "to": "18:00:00", "fee_type": "Free", "sessions": [{"session_id": "77aec12a-f9cb-4652-9ef8-6078eb288a97", "date": "03-05-2021", "available_capacity": 7, "min_age_limit": 45, "vaccine": "", "slots": ["09:00AM-11:00AM", "11:00AM-01:00PM", "01:00PM-03:00PM", "03:00PM-06:00PM"]}]}, {"center_id": 622390, "name": "Chakrod SHC CHO", "state_name": "Madhya Pradesh", "district_name": "Shajapur", "block_name": "SHUJALPUR", "pincode": 465335, "lat": 23, "long": 76, "from": "09:00:00", "to": "18:00:00", "fee_type": "Free", "sessions": [{"session_id": "ec885a93-fd65-4254-82eb-80a10959f1e0", "date": "03-05-2021", "available_capacity": 10, "min_age_limit": 45, "vaccine": "", "slots": ["09:00AM-11:00AM", "11:00AM-01:00PM", "01:00PM-03:00PM", "03:00PM-06:00PM"]}]}, {"center_id": 625676, "name": "UPHC Shajapur", "state_name": "Madhya Pradesh", "district_name": "Shajapur", "block_name": "SHAJAPUR", "pincode": 465001, "lat": 23, "long": 76, "from": "09:00:00", "to": "18:00:00", "fee_type": "Free", "sessions": [{"session_id": "6b950429-b8ff-4c97-996c-a7da8edb8475", "date": "03-05-2021", "available_capacity": 46, "min_age_limit": 45, "vaccine": "", "slots": ["09:00AM-11:00AM", "11:00AM-01:00PM", "01:00PM-03:00PM", "03:00PM-06:00PM"]}, {"session_id": "fed049c6-b647-4c1f-b6ae-e2ca37527d6d", "date": "04-05-2021", "available_capacity": 20, "min_age_limit": 45, "vaccine": "", "slots": ["09:00AM-11:00AM", "11:00AM-01:00PM", "01:00PM-03:00PM", "03:00PM-06:00PM"]}, {"session_id": "e834be93-817c-4d1b-a2c5-ba0464b1d270", "date": "05-05-2021", "available_capacity": 20, "min_age_limit": 45, "vaccine": "", "slots": ["09:00AM-11:00AM", "11:00AM-01:00PM", "01:00PM-03:00PM", "03:00PM-06:00PM"]}, {"session_id": "3c8d0630-9dde-4b87-86f4-0cb271528d68", "date": "06-05-2021", "available_capacity": 10, "min_age_limit": 45, "vaccine": "", "slots": ["09:00AM-11:00AM", "11:00AM-01:00PM", "01:00PM-03:00PM", "03:00PM-06:00PM"]}]}, {"center_id": 619840, "name": "JHONKAR PHC", "state_name": "Madhya Pradesh", "district_name": "Shajapur", "block_name": "SHAJAPUR", "pincode": 465106, "lat": 23, "long": 76, "from": "09:00:00", "to": "18:00:00", "fee_type": "Free", "sessions": [{"session_id": "837777d1-5139-4594-8eee-8b8002bb59df", "date": "03-05-2021", "available_capacity": 7, "min_age_limit": 45, "vaccine": "", "slots": ["09:00AM-11:00AM", "11:00AM-01:00PM", "01:00PM-03:00PM", "03:00PM-06:00PM"]}, {"session_id": "bc106639-bf9e-4a6e-b7d3-594012c50bb6", "date": "05-05-2021", "available_capacity": 10, "min_age_limit": 45, "vaccine": "", "slots": ["09:00AM-11:00AM", "11:00AM-01:00PM", "01:00PM-03:00PM", "03:00PM-06:00PM"]}]}, {"center_id": 574447, "name": "Dopada CCP", "state_name": "Madhya Pradesh", "district_name": "Shajapur", "block_name": "Moman Badodiya", "pincode": 465001, "lat": 23, "long": 76, "from": "09:00:00", "to": "18:00:00", "fee_type": "Free", "sessions": [{"session_id": "ec0ea5b3-596a-4dcc-8d13-c18103d6420d", "date": "03-05-2021", "available_capacity": 4, "min_age_limit": 45, "vaccine": "", "slots": ["09:00AM-11:00AM", "11:00AM-01:00PM", "01:00PM-03:00PM", "03:00PM-06:00PM"]}]}, {"center_id": 619888, "name": "Polaykhurd PHC", "state_name": "Madhya Pradesh", "district_name": "Shajapur", "block_name": "Moman Badodiya", "pincode": 465223, "lat": 23, "long": 76, "from": "09:00:00", "to": "18:00:00", "fee_type": "Free", "sessions": [{"session_id": "533e9229-3b27-4435-9e33-813109627e89", "date": "03-05-2021", "available_capacity": 10, "min_age_limit": 45, "vaccine": "", "slots": ["09:00AM-11:00AM", "11:00AM-01:00PM", "01:00PM-03:00PM", "03:00PM-06:00PM"]}]}, {"center_id": 655876, "name": "Mitera SHC", "state_name": "Madhya Pradesh", "district_name": "Shajapur", "block_name": "SHUJALPUR", "pincode": 465227, "lat": 23, "long": 76, "from": "09:00:00", "to": "18:00:00", "fee_type": "Free", "sessions": [{"session_id": "14b49e6f-0b16-4e05-abeb-12d79162e53b", "date": "03-05-2021", "available_capacity": 10, "min_age_limit": 45, "vaccine": "", "slots": ["09:00AM-11:00AM", "11:00AM-01:00PM", "01:00PM-03:00PM", "03:00PM-06:00PM"]}]}, {"center_id": 620999, "name": "Ranthbhanwar", "state_name": "Madhya Pradesh", "district_name": "Shajapur", "block_name": "SHAJAPUR", "pincode": 465110, "lat": 23, "long": 76, "from": "09:00:00", "to": "18:00:00", "fee_type": "Free", "sessions": [{"session_id": "5437cab6-bb8b-4fc1-933d-f15ce8089781", "date": "03-05-2021", "available_capacity": 9, "min_age_limit": 45, "vaccine": "", "slots": ["09:00AM-11:00AM", "11:00AM-01:00PM", "01:00PM-03:00PM", "03:00PM-06:00PM"]}]}, {"center_id": 574374, "name": "Mohna PHC CCP", "state_name": "Madhya Pradesh", "district_name": "Shajapur", "block_name": "Moman Badodiya", "pincode": 465226, "lat": 23, "long": 75, "from": "09:00:00", "to": "18:00:00", "fee_type": "Free", "sessions": [{"session_id": "a27976f8-b9ab-4a8c-91f0-a593382fc8cb", "date": "03-05-2021", "available_capacity": 8, "min_age_limit": 45, "vaccine": "", "slots": ["09:00AM-11:00AM", "11:00AM-01:00PM", "01:00PM-03:00PM", "03:00PM-06:00PM"]}, {"session_id": "6dfc7255-f7d7-4b73-81e8-d3af2dfa10bd", "date": "05-05-2021", "available_capacity": 8, "min_age_limit": 45, "vaccine": "", "slots": ["09:00AM-11:00AM", "11:00AM-01:00PM", "01:00PM-03:00PM", "03:00PM-06:00PM"]}]}, {"center_id": 655985, "name": "Lahori SHC", "state_name": "Madhya Pradesh", "district_name": "Shajapur", "block_name": "SHAJAPUR", "pincode": 465220, "lat": 23, "long": 76, "from": "09:00:00", "to": "18:00:00", "fee_type": "Free", "sessions": [{"session_id": "2c83ee40-2c41-41ce-9c48-7b36c2e31eed", "date": "03-05-2021", "available_capacity": 7, "min_age_limit": 45, "vaccine": "", "slots": ["09:00AM-11:00AM", "11:00AM-01:00PM", "01:00PM-03:00PM", "03:00PM-06:00PM"]}]}, {"center_id": 655433, "name": "Jaloda SHC", "state_name": "Madhya Pradesh", "district_name": "Shajapur", "block_name": "Moman Badodiya", "pincode": 465001, "lat": 23, "long": 76, "from": "09:00:00", "to": "18:00:00", "fee_type": "Free", "sessions": [{"session_id": "c6700427-b470-49eb-82fc-abd6f4e6c7c9", "date": "03-05-2021", "available_capacity": 9, "min_age_limit": 45, "vaccine": "", "slots": ["09:00AM-11:00AM", "11:00AM-01:00PM", "01:00PM-03:00PM", "03:00PM-06:00PM"]}]}, {"center_id": 615799, "name": "Akodia CHC", "state_name": "Madhya Pradesh", "district_name": "Shajapur", "block_name": "SHUJALPUR", "pincode": 465223, "lat": 23, "long": 76, "from": "09:00:00", "to": "18:00:00", "fee_type": "Free", "sessions": [{"session_id": "97bf86dc-5105-4f7a-b2ab-8c2b2f91a68a", "date": "03-05-2021", "available_capacity": 17, "min_age_limit": 45, "vaccine": "", "slots": ["09:00AM-11:00AM", "11:00AM-01:00PM", "01:00PM-03:00PM", "03:00PM-06:00PM"]}, {"session_id": "a628d9f2-4699-46d0-9e04-8bbfc3d59e9e", "date": "04-05-2021", "available_capacity": 17, "min_age_limit": 45, "vaccine": "", "slots": ["09:00AM-11:00AM", "11:00AM-01:00PM", "01:00PM-03:00PM", "03:00PM-06:00PM"]}, {"session_id": "3b169d9b-391e-4f59-93db-a8d43395f0a6", "date": "05-05-2021", "available_capacity": 14, "min_age_limit": 45, "vaccine": "", "slots": ["09:00AM-11:00AM", "11:00AM-01:00PM", "01:00PM-03:00PM", "03:00PM-06:00PM"]}]}, {"center_id": 655995, "name": "Panwadi SHC", "state_name": "Madhya Pradesh", "district_name": "Shajapur", "block_name": "SHAJAPUR", "pincode": 465001, "lat": 23, "long": 76, "from": "09:00:00", "to": "18:00:00", "fee_type": "Free", "sessions": [{"session_id": "6181e85c-7d51-420d-896c-a46571b3d286", "date": "03-05-2021", "available_capacity": 2, "min_age_limit": 45, "vaccine": "", "slots": ["09:00AM-11:00AM", "11:00AM-01:00PM", "01:00PM-03:00PM", "03:00PM-06:00PM"]}]}, {"center_id": 669674, "name": "Satgonw SHC", "state_name": "Madhya Pradesh", "district_name": "Shajapur", "block_name": "SHAJAPUR", "pincode": 465001, "lat": 23, "long": 76, "from": "09:00:00", "to": "18:00:00", "fee_type": "Free", "sessions": [{"session_id": "60782ad9-82af-4827-957d-fe79fcdd36b9", "date": "03-05-2021", "available_capacity": 10, "min_age_limit": 45, "vaccine": "", "slots": ["09:00AM-11:00AM", "11:00AM-01:00PM", "01:00PM-03:00PM", "03:00PM-06:00PM"]}]}, {"center_id": 620856, "name": "Ugli SHC CHO", "state_name": "Madhya Pradesh", "district_name": "Shajapur", "block_name": "SHUJALPUR", "pincode": 465337, "lat": 23, "long": 76, "from": "09:00:00", "to": "18:00:00", "fee_type": "Free", "sessions": [{"session_id": "1da2ce9a-f02f-4ca8-82bf-66394acdd8dc", "date": "03-05-2021", "available_capacity": 3, "min_age_limit": 45, "vaccine": "", "slots": ["09:00AM-11:00AM", "11:00AM-01:00PM", "01:00PM-03:00PM", "03:00PM-06:00PM"]}]}, {"center_id": 655878, "name": "Binaya SHC", "state_name": "Madhya Pradesh", "district_name": "Shajapur", "block_name": "SHUJALPUR", "pincode": 465118, "lat": 23, "long": 76, "from": "09:00:00", "to": "18:00:00", "fee_type": "Free", "sessions": [{"session_id": "fab9fadd-0a98-4abd-8eaf-4f0c56a6c076", "date": "03-05-2021", "available_capacity": 10, "min_age_limit": 45, "vaccine": "", "slots": ["09:00AM-11:00AM", "11:00AM-01:00PM", "01:00PM-03:00PM", "03:00PM-06:00PM"]}]}, {"center_id": 655671, "name": "Siloda SHC", "state_name": "Madhya Pradesh", "district_name": "Shajapur", "block_name": "SHUJALPUR", "pincode": 465335, "lat": 0, "long": 0, "from": "09:00:00", "to": "18:00:00", "fee_type": "Free", "sessions": [{"session_id": "7d09400a-a5b0-4c31-b1f8-591b00b7c69b", "date": "03-05-2021", "available_capacity": 9, "min_age_limit": 45, "vaccine": "", "slots": ["09:00AM-11:00AM", "11:00AM-01:00PM", "01:00PM-03:00PM", "03:00PM-06:00PM"]}]}, {"center_id": 655665, "name": "Jhadla SHC", "state_name": "Madhya Pradesh", "district_name": "Shajapur", "block_name": "SHUJALPUR", "pincode": 465333, "lat": 23, "long": 76, "from": "09:00:00", "to": "18:00:00", "fee_type": "Free", "sessions": [{"session_id": "4fc15142-8243-4a0f-ad05-e756b03c0711", "date": "03-05-2021", "available_capacity": 9, "min_age_limit": 45, "vaccine": "", "slots": ["09:00AM-11:00AM", "11:00AM-01:00PM", "01:00PM-03:00PM", "03:00PM-06:00PM"]}]}, {"center_id": 655890, "name": "Kisoni SHC", "state_name": "Madhya Pradesh", "district_name": "Shajapur", "block_name": "SHUJALPUR", "pincode": 465333, "lat": 23, "long": 76, "from": "09:00:00", "to": "18:00:00", "fee_type": "Free", "sessions": [{"session_id": "6fbc46c7-41bc-4c39-805f-381a7a6c565f", "date": "03-05-2021", "available_capacity": 10, "min_age_limit": 45, "vaccine": "", "slots": ["09:00AM-11:00AM", "11:00AM-01:00PM", "01:00PM-03:00PM", "03:00PM-06:00PM"]}]}, {"center_id": 621508, "name": "Bikla Khedi SHC CHO", "state_name": "Madhya Pradesh", "district_name": "Shajapur", "block_name": "SHAJAPUR", "pincode": 465110, "lat": 23, "long": 76, "from": "09:00:00", "to": "18:00:00", "fee_type": "Free", "sessions": [{"session_id": "d23af9f5-bbcc-4460-bfad-a320734ed4fd", "date": "03-05-2021", "available_capacity": 6, "min_age_limit": 45, "vaccine": "", "slots": ["09:00AM-11:00AM", "11:00AM-01:00PM", "01:00PM-03:00PM", "03:00PM-06:00PM"]}]}, {"center_id": 656287, "name": "Nipaniya Dhakad", "state_name": "Madhya Pradesh", "district_name": "Shajapur", "block_name": "SHAJAPUR", "pincode": 465113, "lat": 23, "long": 76, "from": "09:00:00", "to": "18:00:00", "fee_type": "Free", "sessions": [{"session_id": "7329a572-b5c0-4aa1-8b3f-963241d4ec09", "date": "03-05-2021", "available_capacity": 10, "min_age_limit": 45, "vaccine": "", "slots": ["09:00AM-11:00AM", "11:00AM-01:00PM", "01:00PM-03:00PM", "03:00PM-06:00PM"]}]}, {"center_id": 655976, "name": "Gopipur SHC", "state_name": "Madhya Pradesh", "district_name": "Shajapur", "block_name": "SHAJAPUR", "pincode": 465001, "lat": 23, "long": 76, "from": "09:00:00", "to": "18:00:00", "fee_type": "Free", "sessions": [{"session_id": "baf02480-1346-4ef2-8300-a8f409ccfd91", "date": "03-05-2021", "available_capacity": 9, "min_age_limit": 45, "vaccine": "", "slots": ["09:00AM-11:00AM", "11:00AM-01:00PM", "01:00PM-03:00PM", "03:00PM-06:00PM"]}]}, {"center_id": 622375, "name": "Choslakulmi SHC CHO", "state_name": "Madhya Pradesh", "district_name": "Shajapur", "block_name": "SHAJAPUR", "pincode": 465110, "lat": 23, "long": 76, "from": "09:00:00", "to": "18:00:00", "fee_type": "Free", "sessions": [{"session_id": "378c010d-0b47-47c3-b76f-2642481c749e", "date": "03-05-2021", "available_capacity": 10, "min_age_limit": 45, "vaccine": "", "slots": ["09:00AM-11:00AM", "11:00AM-01:00PM", "01:00PM-03:00PM", "03:00PM-06:00PM"]}]}, {"center_id": 574312, "name": "Moman Barodiya CCP", "state_name": "Madhya Pradesh", "district_name": "Shajapur", "block_name": "Moman Badodiya", "pincode": 465226, "lat": 23, "long": 76, "from": "09:00:00", "to": "18:00:00", "fee_type": "Free", "sessions": [{"session_id": "bc7c75de-38db-4a74-a848-72a89ac3be46", "date": "03-05-2021", "available_capacity": 7, "min_age_limit": 45, "vaccine": "", "slots": ["09:00AM-11:00AM", "11:00AM-01:00PM", "01:00PM-03:00PM", "03:00PM-06:00PM"]}, {"session_id": "958aa8a5-93fe-474d-a40c-0af5dfa281f6", "date": "04-05-2021", "available_capacity": 20, "min_age_limit": 45, "vaccine": "", "slots": ["09:00AM-11:00AM", "11:00AM-01:00PM", "01:00PM-03:00PM", "03:00PM-06:00PM"]}, {"session_id": "19797493-5791-4fb1-a5c6-4b61dd74173a", "date": "05-05-2021", "available_capacity": 15, "min_age_limit": 45, "vaccine": "", "slots": ["09:00AM-11:00AM", "11:00AM-01:00PM", "01:00PM-03:00PM", "03:00PM-06:00PM"]}]}, {"center_id": 621666, "name": "Siroliya SHC CHO", "state_name": "Madhya Pradesh", "district_name": "Shajapur", "block_name": "SHAJAPUR", "pincode": 465106, "lat": 23, "long": 76, "from": "09:00:00", "to": "18:00:00", "fee_type": "Free", "sessions": [{"session_id": "8f98da6e-92d4-4e0f-89c3-06a08d37de44", "date": "03-05-2021", "available_capacity": 9, "min_age_limit": 45, "vaccine": "", "slots": ["09:00AM-11:00AM", "11:00AM-01:00PM", "01:00PM-03:00PM", "03:00PM-06:00PM"]}]}, {"center_id": 656240, "name": "Sajod SHC", "state_name": "Madhya Pradesh", "district_name": "Shajapur", "block_name": "SHAJAPUR", "pincode": 465001, "lat": 23, "long": 76, "from": "09:00:00", "to": "18:00:00", "fee_type": "Free", "sessions": [{"session_id": "67368f00-c8f0-4e4f-8de9-7f7817aa8f69", "date": "03-05-2021", "available_capacity": 10, "min_age_limit": 45, "vaccine": "", "slots": ["09:00AM-11:00AM", "11:00AM-01:00PM", "01:00PM-03:00PM", "03:00PM-06:00PM"]}]}, {"center_id": 574471, "name": "Maxi CCP", "state_name": "Madhya Pradesh", "district_name": "Shajapur", "block_name": "SHAJAPUR", "pincode": 465106, "lat": 23, "long": 76, "from": "09:00:00", "to": "18:00:00", "fee_type": "Free", "sessions": [{"session_id": "3113bc80-5bf6-43a8-b015-a3505f43acef", "date": "03-05-2021", "available_capacity": 1, "min_age_limit": 45, "vaccine": "", "slots": ["09:00AM-11:00AM", "11:00AM-01:00PM", "01:00PM-03:00PM", "03:00PM-06:00PM"]}, {"session_id": "7c92a863-6d87-4803-9f9a-02fa24db13ba", "date": "05-05-2021", "available_capacity": 10, "min_age_limit": 45, "vaccine": "", "slots": ["09:00AM-11:00AM", "11:00AM-01:00PM", "01:00PM-03:00PM", "03:00PM-06:00PM"]}]}, {"center_id": 655990, "name": "Kapaliya SHC", "state_name": "Madhya Pradesh", "district_name": "Shajapur", "block_name": "SHAJAPUR", "pincode": 465106, "lat": 23, "long": 76, "from": "09:00:00", "to": "18:00:00", "fee_type": "Free", "sessions": [{"session_id": "a53d4cad-7cf6-4fb9-8a64-9ce35a910627", "date": "03-05-2021", "available_capacity": 9, "min_age_limit": 45, "vaccine": "", "slots": ["09:00AM-11:00AM", "11:00AM-01:00PM", "01:00PM-03:00PM", "03:00PM-06:00PM"]}]}, {"center_id": 655623, "name": "Khadi SHC", "state_name": "Madhya Pradesh", "district_name": "Shajapur", "block_name": "SHUJALPUR", "pincode": 465116, "lat": 23, "long": 76, "from": "09:00:00", "to": "18:00:00", "fee_type": "Free", "sessions": [{"session_id": "594077f0-25d1-452c-bb10-46b80e5b59ec", "date": "03-05-2021", "available_capacity": 10, "min_age_limit": 45, "vaccine": "", "slots": ["09:00AM-11:00AM", "11:00AM-01:00PM", "01:00PM-03:00PM", "03:00PM-06:00PM"]}]}, {"center_id": 669698, "name": "Chouma SHC", "state_name": "Madhya Pradesh", "district_name": "Shajapur", "block_name": "Moman Badodiya", "pincode": 465226, "lat": 23, "long": 76, "from": "09:00:00", "to": "18:00:00", "fee_type": "Free", "sessions": [{"session_id": "d71e7937-b286-4cd3-b92b-335ec6feabe1", "date": "03-05-2021", "available_capacity": 10, "min_age_limit": 45, "vaccine": "", "slots": ["09:00AM-11:00AM", "11:00AM-01:00PM", "01:00PM-03:00PM", "03:00PM-06:00PM"]}]}, {"center_id": 656255, "name": "Akya SHC", "state_name": "Madhya Pradesh", "district_name": "Shajapur", "block_name": "SHAJAPUR", "pincode": 465001, "lat": 23, "long": 76, "from": "09:00:00", "to": "18:00:00", "fee_type": "Free", "sessions": [{"session_id": "dfb26bd5-601b-4d7d-a07b-f11a29a4a8c5", "date": "03-05-2021", "available_capacity": 6, "min_age_limit": 45, "vaccine": "", "slots": ["09:00AM-11:00AM", "11:00AM-01:00PM", "01:00PM-03:00PM", "03:00PM-06:00PM"]}]}, {"center_id": 561308, "name": "Trama Center Shajapur", "state_name": "Madhya Pradesh", "district_name": "Shajapur", "block_name": "SHAJAPUR", "pincode": 465001, "lat": 23, "long": 76, "from": "09:00:00", "to": "18:00:00", "fee_type": "Free", "sessions": [{"session_id": "b34864fe-6e3a-4ca7-a8c8-71df919766a4", "date": "03-05-2021", "available_capacity": 74, "min_age_limit": 45, "vaccine": "", "slots": ["09:00AM-11:00AM", "11:00AM-01:00PM", "01:00PM-03:00PM", "03:00PM-06:00PM"]}, {"session_id": "675578d6-2d58-4b05-bed4-0e9bbf1955ca", "date": "05-05-2021", "available_capacity": 70, "min_age_limit": 45, "vaccine": "", "slots": ["09:00AM-11:00AM", "11:00AM-01:00PM", "01:00PM-03:00PM", "03:00PM-06:00PM"]}, {"session_id": "e4991e7d-f36b-4420-825b-f00fd78b97c2", "date": "06-05-2021", "available_capacity": 50, "min_age_limit": 45, "vaccine": "", "slots": ["09:00AM-11:00AM", "11:00AM-01:00PM", "01:00PM-03:00PM", "03:00PM-06:00PM"]}]}, {"center_id": 621721, "name": "Tilawat Govind SHC CHO", "state_name": "Madhya Pradesh", "district_name": "Shajapur", "block_name": "SHAJAPUR", "pincode": 465110, "lat": 23, "long": 76, "from": "09:00:00", "to": "18:00:00", "fee_type": "Free", "sessions": [{"session_id": "d4d25138-98e5-49ce-9978-cbdd21774b4f", "date": "03-05-2021", "available_capacity": 10, "min_age_limit": 45, "vaccine": "", "slots": ["09:00AM-11:00AM", "11:00AM-01:00PM", "01:00PM-03:00PM", "03:00PM-06:00PM"]}]}, {"center_id": 655467, "name": "Karju SHC", "state_name": "Madhya Pradesh", "district_name": "Shajapur", "block_name": "Moman Badodiya", "pincode": 465226, "lat": 23, "long": 76, "from": "09:00:00", "to": "18:00:00", "fee_type": "Free", "sessions": [{"session_id": "5ab55586-b91e-4abc-9ecb-9a20117488f1", "date": "03-05-2021", "available_capacity": 9, "min_age_limit": 45, "vaccine": "", "slots": ["09:00AM-11:00AM", "11:00AM-01:00PM", "01:00PM-03:00PM", "03:00PM-06:00PM"]}]}, {"center_id": 655884, "name": "Laharkheda SHC", "state_name": "Madhya Pradesh", "district_name": "Shajapur", "block_name": "SHUJALPUR", "pincode": 465227, "lat": 23, "long": 76, "from": "09:00:00", "to": "18:00:00", "fee_type": "Free", "sessions": [{"session_id": "88d69a0c-8635-4395-b8c3-e2dcf7de7b69", "date": "03-05-2021", "available_capacity": 10, "min_age_limit": 45, "vaccine": "", "slots": ["09:00AM-11:00AM", "11:00AM-01:00PM", "01:00PM-03:00PM", "03:00PM-06:00PM"]}]}, {"center_id": 562815, "name": "Sujalpur Mandi New Hospital", "state_name": "Madhya Pradesh", "district_name": "Shajapur", "block_name": "SHUJALPUR", "pincode": 465333, "lat": 23, "long": 76, "from": "09:00:00", "to": "18:00:00", "fee_type": "Free", "sessions": [{"session_id": "546c60c0-6e59-43b7-be28-1f9457b95a23", "date": "04-05-2021", "available_capacity": 29, "min_age_limit": 45, "vaccine": "", "slots": ["09:00AM-11:00AM", "11:00AM-01:00PM", "01:00PM-03:00PM", "03:00PM-06:00PM"]}, {"session_id": "e172d1df-54e3-4ad6-97cd-5444f26979d8", "date": "06-05-2021", "available_capacity": 26, "min_age_limit": 45, "vaccine": "", "slots": ["09:00AM-11:00AM", "11:00AM-01:00PM", "01:00PM-03:00PM", "03:00PM-06:00PM"]}]}, {"center_id": 672804, "name": "Jyoti Nagar HSS", "state_name": "Madhya Pradesh", "district_name": "Shajapur", "block_name": "SHAJAPUR", "pincode": 465001, "lat": 23, "long": 76, "from": "09:00:00", "to": "18:00:00", "fee_type": "Free", "sessions": [{"session_id": "33371248-fded-4b63-9172-a4df2ae0b0a8", "date": "05-05-2021", "available_capacity": 47, "min_age_limit": 45, "vaccine": "", "slots": ["09:00AM-11:00AM", "11:00AM-01:00PM", "01:00PM-03:00PM", "03:00PM-06:00PM"]}, {"session_id": "3bb40bec-a58e-4c6b-8e3c-6bed36ebffae", "date": "06-05-2021", "available_capacity": 10, "min_age_limit": 45, "vaccine": "", "slots": ["09:00AM-11:00AM", "11:00AM-01:00PM", "01:00PM-03:00PM", "03:00PM-06:00PM"]}]}, {"center_id": 620362, "name": "Awantipur Barodiya PHC", "state_name": "Madhya Pradesh", "district_name": "Shajapur", "block_name": "SHUJALPUR", "pincode": 465116, "lat": 23, "long": 76, "from": "09:00:00", "to": "18:00:00", "fee_type": "Free", "sessions": [{"session_id": "43179b64-bcee-473a-a55b-4393549682ef", "date": "05-05-2021", "available_capacity": 10, "min_age_limit": 45, "vaccine": "", "slots": ["09:00AM-11:00AM", "11:00AM-01:00PM", "01:00PM-03:00PM", "03:00PM-06:00PM"]}]}, {"center_id": 672810, "name": "Community Hall Nagar Palika", "state_name": "Madhya Pradesh", "district_name": "Shajapur", "block_name": "SHAJAPUR", "pincode": 465001, "lat": 23, "long": 76, "from": "09:00:00", "to": "18:00:00", "fee_type": "Free", "sessions": [{"session_id": "7d5528a9-4378-49d4-90d2-b1a35d098b97", "date": "05-05-2021", "available_capacity": 47, "min_age_limit": 45, "vaccine": "", "slots": ["09:00AM-11:00AM", "11:00AM-01:00PM", "01:00PM-03:00PM", "03:00PM-06:00PM"]}, {"session_id": "75efb182-bf96-4001-af7c-e0cff9db7c1d", "date": "06-05-2021", "available_capacity": 9, "min_age_limit": 45, "vaccine": "", "slots": ["09:00AM-11:00AM", "11:00AM-01:00PM", "01:00PM-03:00PM", "03:00PM-06:00PM"]}]}, {"center_id": 672817, "name": "Vazirpura Old Hospital", "state_name": "Madhya Pradesh", "district_name": "Shajapur", "block_name": "SHAJAPUR", "pincode": 465001, "lat": 23, "long": 76, "from": "09:00:00", "to": "18:00:00", "fee_type": "Free", "sessions": [{"session_id": "6a37cdc7-e170-4456-8cc0-492474cca851", "date": "05-05-2021", "available_capacity": 46, "min_age_limit": 45, "vaccine": "", "slots": ["09:00AM-11:00AM", "11:00AM-01:00PM", "01:00PM-03:00PM", "03:00PM-06:00PM"]}, {"session_id": "c90cd678-9965-4a49-8085-496e0ac1225d", "date": "06-05-2021", "available_capacity": 10, "min_age_limit": 45, "vaccine": "", "slots": ["09:00AM-11:00AM", "11:00AM-01:00PM", "01:00PM-03:00PM", "03:00PM-06:00PM"]}]}, {"center_id": 674234, "name": "Teliwada School", "state_name": "Madhya Pradesh", "district_name": "Shajapur", "block_name": "SHAJAPUR", "pincode": 465001, "lat": 23, "long": 76, "from": "09:00:00", "to": "18:00:00", "fee_type": "Free", "sessions": [{"session_id": "3fcd1a3d-a5e1-4e5e-b9b3-22acc8c628bf", "date": "06-05-2021", "available_capacity": 10, "min_age_limit": 45, "vaccine": "", "slots": ["09:00AM-11:00AM", "11:00AM-01:00PM", "01:00PM-03:00PM", "03:00PM-06:00PM"]}]}]