[{"center_id": 617673, "name": "HCW THANA", "state_name": "Uttar Pradesh", "district_name": "Unnao", "block_name": "Sikandarpur Sarosi", "pincode": 209801, "lat": 26, "long": 80, "from": "09:00:00", "to": "18:00:00", "fee_type": "Free", "sessions": [{"session_id": "fb8929ec-bfa7-4103-87ec-0aec86e2c730", "date": "17-05-2021", "available_capacity": 50, "min_age_limit": 45, "vaccine": "", "slots": ["09:00AM-11:00AM", "11:00AM-01:00PM", "01:00PM-03:00PM", "03:00PM-06:00PM"]}]}, {"center_id": 677061, "name": "UPHC MOTI NAGAR COVISHIELD", "state_name": "Uttar Pradesh", "district_name": "Unnao", "block_name": "Unnao Urban", "pincode": 209801, "lat": 26, "long": 80, "from": "09:00:00", "to": "18:00:00", "fee_type": "Free", "sessions": [{"session_id": "ae208e4a-3242-47c0-b1fa-eca712913f11", "date": "19-05-2021", "available_capacity": 44, "min_age_limit": 45, "vaccine": "", "slots": ["09:00AM-11:00AM", "11:00AM-01:00PM", "01:00PM-03:00PM", "03:00PM-06:00PM"]}, {"session_id": "00e75bdf-89b5-4b6d-8d5e-e7fcf29e2a62", "date": "20-05-2021", "available_capacity": 49, "min_age_limit": 45, "vaccine": "", "slots": ["09:00AM-11:00AM", "11:00AM-01:00PM", "01:00PM-03:00PM", "03:00PM-06:00PM"]}]}]