[{"center_id": 19656, "name": "Bidhlan PHC", "state_name": "Haryana", "district_name": "Sonipat", "block_name": "Kharkhoda", "pincode": 131402, "lat": 28, "long": 76, "from": "09:00:00", "to": "18:00:00", "fee_type": "Free", "sessions": [{"session_id": "37fb8e69-d6e3-4f1b-8573-e48c84433987", "date": "11-05-2021", "available_capacity": 50, "min_age_limit": 45, "vaccine": "", "slots": ["09:00AM-11:00AM", "11:00AM-01:00PM", "01:00PM-03:00PM", "03:00PM-06:00PM"]}, {"session_id": "24f423e5-e0b8-4cfa-98ff-2ac46b3cdd6a", "date": "12-05-2021", "available_capacity": 50, "min_age_limit": 45, "vaccine": "", "slots": ["09:00AM-11:00AM", "11:00AM-01:00PM", "01:00PM-03:00PM", "03:00PM-06:00PM"]}]}, {"center_id": 565135, "name": "Kharkhoda CHC", "state_name": "Haryana", "district_name": "Sonipat", "block_name": "Kharkhoda", "pincode": 131402, "lat": 28, "long": 76, "from": "09:00:00", "to": "18:00:00", "fee_type": "Free", "sessions": [{"session_id": "688c9cc5-1420-4f13-be50-2d7d13227f2a", "date": "11-05-2021", "available_capacity": 45, "min_age_limit": 45, "vaccine": "", "slots": ["09:00AM-11:00AM", "11:00AM-01:00PM", "01:00PM-03:00PM", "03:00PM-06:00PM"]}]}, {"center_id": 627239, "name": "Phc Sisana", "state_name": "Haryana", "district_name": "Sonipat", "block_name": "Kharkhoda", "pincode": 131402, "lat": 0, "long": 0, "from": "09:00:00", "to": "18:00:00", "fee_type": "Free", "sessions": [{"session_id": "916de7a5-3a78-4830-aa35-71941d989365", "date": "11-05-2021", "available_capacity": 50, "min_age_limit": 45, "vaccine": "", "slots": ["09:00AM-11:00AM", "11:00AM-01:00PM", "01:00PM-03:00PM", "03:00PM-06:00PM"]}]}]