[{"center_id": 645024, "name": "Kanadukathan GH", "state_name": "Tamil Nadu", "district_name": "Sivaganga", "block_name": "Sakkottai", "pincode": 630003, "lat": 0, "long": 0, "from": "09:00:00", "to": "18:00:00", "fee_type": "Free", "sessions": [{"session_id": "18d9c2f3-93f8-4977-ac94-7b4ee8f0ba4c", "date": "07-05-2021", "available_capacity": 50, "min_age_limit": 45, "vaccine": "", "slots": ["09:00AM-11:00AM", "11:00AM-01:00PM", "01:00PM-03:00PM", "03:00PM-06:00PM"]}]}, {"center_id": 671384, "name": "Ilayangudi Gh Covaxin", "state_name": "Tamil Nadu", "district_name": "Sivaganga", "block_name": "Ilayangudi", "pincode": 630105, "lat": 0, "long": 0, "from": "09:00:00", "to": "18:00:00", "fee_type": "Free", "sessions": [{"session_id": "53595bf5-4189-423e-a630-917d2d188cd3", "date": "07-05-2021", "available_capacity": 50, "min_age_limit": 45, "vaccine": "", "slots": ["09:00AM-11:00AM", "11:00AM-01:00PM", "01:00PM-03:00PM", "03:00PM-06:00PM"]}, {"session_id": "091ad1d7-ceea-4254-92d2-6d7191c1d31e", "date": "09-05-2021", "available_capacity": 50, "min_age_limit": 45, "vaccine": "", "slots": ["09:00AM-11:00AM", "11:00AM-01:00PM", "01:00PM-03:00PM", "03:00PM-06:00PM"]}, {"session_id": "e782d6f0-cfa5-406f-aa62-4dbaacdfd5d0", "date": "10-05-2021", "available_capacity": 50, "min_age_limit": 45, "vaccine": "", "slots": ["09:00AM-11:00AM", "11:00AM-01:00PM", "01:00PM-03:00PM", "03:00PM-06:00PM"]}, {"session_id": "65d33e90-7e5e-4e52-a714-26a4fc14c38c", "date": "11-05-2021", "available_capacity": 50, "min_age_limit": 45, "vaccine": "", "slots": ["09:00AM-11:00AM", "11:00AM-01:00PM", "01:00PM-03:00PM", "03:00PM-06:00PM"]}, {"session_id": "523f2377-6eae-46c1-bf2a-728260092cab", "date": "12-05-2021", "available_capacity": 50, "min_age_limit": 45, "vaccine": "", "slots": ["09:00AM-11:00AM", "11:00AM-01:00PM", "01:00PM-03:00PM", "03:00PM-06:00PM"]}, {"session_id": "6e818186-f2d6-491a-babe-3dde5ee46c59", "date": "13-05-2021", "available_capacity": 50, "min_age_limit": 45, "vaccine": "", "slots": ["09:00AM-11:00AM", "11:00AM-01:00PM", "01:00PM-03:00PM", "03:00PM-06:00PM"]}]}, {"center_id": 673863, "name": "KARTHIK HOSPITAL COVAXIN", "state_name": "Tamil Nadu", "district_name": "Sivaganga", "block_name": "Sivaganga", "pincode": 630561, "lat": 0, "long": 0, "from": "09:00:00", "to": "18:00:00", "fee_type": "Free", "sessions": [{"session_id": "d50428cf-a51c-47e3-aaab-641ce7987431", "date": "07-05-2021", "available_capacity": 50, "min_age_limit": 45, "vaccine": "", "slots": ["09:00AM-11:00AM", "11:00AM-01:00PM", "01:00PM-03:00PM", "03:00PM-06:00PM"]}]}, {"center_id": 655281, "name": "Senthil Hospital Covaxin", "state_name": "Tamil Nadu", "district_name": "Sivaganga", "block_name": "Devakottai", "pincode": 630561, "lat": 0, "long": 0, "from": "09:00:00", "to": "18:00:00", "fee_type": "Free", "sessions": [{"session_id": "03759719-e32a-41f4-846d-abd0427026f5", "date": "07-05-2021", "available_capacity": 50, "min_age_limit": 45, "vaccine": "", "slots": ["09:00AM-11:00AM", "11:00AM-01:00PM", "01:00PM-03:00PM", "03:00PM-06:00PM"]}, {"session_id": "df4478ae-edb4-4bec-8040-99034844d9eb", "date": "08-05-2021", "available_capacity": 50, "min_age_limit": 45, "vaccine": "", "slots": ["09:00AM-11:00AM", "11:00AM-01:00PM", "01:00PM-03:00PM", "03:00PM-06:00PM"]}, {"session_id": "0a7e5e09-9511-44b8-95c2-1ed2ea3ac082", "date": "09-05-2021", "available_capacity": 50, "min_age_limit": 45, "vaccine": "", "slots": ["09:00AM-11:00AM", "11:00AM-01:00PM", "01:00PM-03:00PM", "03:00PM-06:00PM"]}]}, {"center_id": 671647, "name": "Pallathur Covaxin", "state_name": "Tamil Nadu", "district_name": "Sivaganga", "block_name": "Thiruppathur", "pincode": 630003, "lat": 0, "long": 0, "from": "09:00:00", "to": "18:00:00", "fee_type": "Free", "sessions": [{"session_id": "eb056c1c-84a2-4784-8428-ec1ca0d6294e", "date": "07-05-2021", "available_capacity": 50, "min_age_limit": 45, "vaccine": "", "slots": ["09:00AM-11:00AM", "11:00AM-01:00PM", "01:00PM-03:00PM", "03:00PM-06:00PM"]}, {"session_id": "d3b0bccb-80e0-4fc2-922f-12ef7ea35892", "date": "08-05-2021", "available_capacity": 50, "min_age_limit": 45, "vaccine": "", "slots": ["09:00AM-11:00AM", "11:00AM-01:00PM", "01:00PM-03:00PM", "03:00PM-06:00PM"]}]}, {"center_id": 655460, "name": "WCH Pallavangudi Covaxin", "state_name": "Tamil Nadu", "district_name": "Sivaganga", "block_name": "kallal", "pincode": 630003, "lat": 0, "long": 0, "from": "09:00:00", "to": "18:00:00", "fee_type": "Free", "sessions": [{"session_id": "2ebf1c4f-0268-4fbe-9b26-db0e783b2d02", "date": "07-05-2021", "available_capacity": 50, "min_age_limit": 45, "vaccine": "", "slots": ["09:00AM-11:00AM", "11:00AM-01:00PM", "01:00PM-03:00PM", "03:00PM-06:00PM"]}, {"session_id": "6b8b4c1a-0ec6-48fa-ab01-1d9e5aadd271", "date": "08-05-2021", "available_capacity": 50, "min_age_limit": 45, "vaccine": "", "slots": ["09:00AM-11:00AM", "11:00AM-01:00PM", "01:00PM-03:00PM", "03:00PM-06:00PM"]}, {"session_id": "1cc7a509-729c-4dd3-9647-4aa2543f0ef1", "date": "09-05-2021", "available_capacity": 50, "min_age_limit": 45, "vaccine": "", "slots": ["09:00AM-11:00AM", "11:00AM-01:00PM", "01:00PM-03:00PM", "03:00PM-06:00PM"]}]}, {"center_id": 675484, "name": "Pacheri Mini Clinic Covaxin", "state_name": "Tamil Nadu", "district_name": "Sivaganga", "block_name": "Manamadurai", "pincode": 630202, "lat": 0, "long": 0, "from": "09:00:00", "to": "18:00:00", "fee_type": "Free", "sessions": [{"session_id": "e7d130d0-f63b-4faf-849d-50b7479a8f77", "date": "07-05-2021", "available_capacity": 50, "min_age_limit": 45, "vaccine": "", "slots": ["09:00AM-11:00AM", "11:00AM-01:00PM", "01:00PM-03:00PM", "03:00PM-06:00PM"]}, {"session_id": "6733b100-9b84-4b5e-9132-90a5a32d1ece", "date": "08-05-2021", "available_capacity": 50, "min_age_limit": 45, "vaccine": "", "slots": ["09:00AM-11:00AM", "11:00AM-01:00PM", "01:00PM-03:00PM", "03:00PM-06:00PM"]}, {"session_id": "d96f129a-9c98-4b53-938d-0b015fc7c457", "date": "09-05-2021", "available_capacity": 50, "min_age_limit": 45, "vaccine": "", "slots": ["09:00AM-11:00AM", "11:00AM-01:00PM", "01:00PM-03:00PM", "03:00PM-06:00PM"]}, {"session_id": "575a37bb-3d2f-4520-a87a-829c88824411", "date": "10-05-2021", "available_capacity": 50, "min_age_limit": 45, "vaccine": "", "slots": ["09:00AM-11:00AM", "11:00AM-01:00PM", "01:00PM-03:00PM", "03:00PM-06:00PM"]}, {"session_id": "bd7afcdd-d971-45eb-9809-4de1f4157729", "date": "11-05-2021", "available_capacity": 50, "min_age_limit": 45, "vaccine": "", "slots": ["09:00AM-11:00AM", "11:00AM-01:00PM", "01:00PM-03:00PM", "03:00PM-06:00PM"]}]}, {"center_id": 671329, "name": "Kalaiyarkovil GH", "state_name": "Tamil Nadu", "district_name": "Sivaganga", "block_name": "Kalayarkoil", "pincode": 630105, "lat": 0, "long": 0, "from": "09:00:00", "to": "18:00:00", "fee_type": "Free", "sessions": [{"session_id": "a1c5ceea-0f75-4991-96db-97e65534ae42", "date": "07-05-2021", "available_capacity": 50, "min_age_limit": 45, "vaccine": "", "slots": ["09:00AM-11:00AM", "11:00AM-01:00PM", "01:00PM-03:00PM", "03:00PM-06:00PM"]}, {"session_id": "4d4af9c4-b287-4a4f-9863-bc22ec4affef", "date": "08-05-2021", "available_capacity": 50, "min_age_limit": 45, "vaccine": "", "slots": ["09:00AM-11:00AM", "11:00AM-01:00PM", "01:00PM-03:00PM", "03:00PM-06:00PM"]}, {"session_id": "15df4d08-de7b-43f7-bbdb-ccbf1779038d", "date": "09-05-2021", "available_capacity": 50, "min_age_limit": 45, "vaccine": "", "slots": ["09:00AM-11:00AM", "11:00AM-01:00PM", "01:00PM-03:00PM", "03:00PM-06:00PM"]}, {"session_id": "a4961060-cc8f-4dd3-9515-60372e3d7378", "date": "10-05-2021", "available_capacity": 50, "min_age_limit": 45, "vaccine": "", "slots": ["09:00AM-11:00AM", "11:00AM-01:00PM", "01:00PM-03:00PM", "03:00PM-06:00PM"]}, {"session_id": "173ec38b-979a-4333-85ee-0ced8f6ba0b2", "date": "11-05-2021", "available_capacity": 50, "min_age_limit": 45, "vaccine": "", "slots": ["09:00AM-11:00AM", "11:00AM-01:00PM", "01:00PM-03:00PM", "03:00PM-06:00PM"]}, {"session_id": "ee9afa0e-6317-4146-b14d-e346f8265e3e", "date": "12-05-2021", "available_capacity": 50, "min_age_limit": 45, "vaccine": "", "slots": ["09:00AM-11:00AM", "11:00AM-01:00PM", "01:00PM-03:00PM", "03:00PM-06:00PM"]}, {"session_id": "d86deda6-b88f-4c4e-a246-f9064894d92a", "date": "13-05-2021", "available_capacity": 50, "min_age_limit": 45, "vaccine": "", "slots": ["09:00AM-11:00AM", "11:00AM-01:00PM", "01:00PM-03:00PM", "03:00PM-06:00PM"]}]}, {"center_id": 678825, "name": "Marudhangudi Phc Covishield", "state_name": "Tamil Nadu", "district_name": "Sivaganga", "block_name": "kallal", "pincode": 630104, "lat": 0, "long": 0, "from": "09:00:00", "to": "18:00:00", "fee_type": "Free", "sessions": [{"session_id": "e8791c4d-9d50-4c47-846a-1548384e23d8", "date": "09-05-2021", "available_capacity": 50, "min_age_limit": 45, "vaccine": "", "slots": ["09:00AM-11:00AM", "11:00AM-01:00PM", "01:00PM-03:00PM", "03:00PM-06:00PM"]}]}, {"center_id": 661605, "name": "Marudhangudi PHC Covaxin", "state_name": "Tamil Nadu", "district_name": "Sivaganga", "block_name": "kallal", "pincode": 630003, "lat": 0, "long": 0, "from": "09:00:00", "to": "18:00:00", "fee_type": "Free", "sessions": [{"session_id": "fa84ac29-c8df-4dac-b9bb-3212a14bdbc5", "date": "09-05-2021", "available_capacity": 50, "min_age_limit": 45, "vaccine": "", "slots": ["09:00AM-11:00AM", "11:00AM-01:00PM", "01:00PM-03:00PM", "03:00PM-06:00PM"]}, {"session_id": "e11b28d1-135f-4780-af37-af9a4cab6a4e", "date": "10-05-2021", "available_capacity": 50, "min_age_limit": 45, "vaccine": "", "slots": ["09:00AM-11:00AM", "11:00AM-01:00PM", "01:00PM-03:00PM", "03:00PM-06:00PM"]}]}, {"center_id": 484883, "name": "Therku Salaigramam", "state_name": "Tamil Nadu", "district_name": "Sivaganga", "block_name": "Ilayangudi", "pincode": 630710, "lat": 0, "long": 0, "from": "09:00:00", "to": "18:00:00", "fee_type": "Free", "sessions": [{"session_id": "6511a318-fc01-4934-82d2-00aa5be6731a", "date": "10-05-2021", "available_capacity": 50, "min_age_limit": 45, "vaccine": "", "slots": ["09:00AM-11:00AM", "11:00AM-01:00PM", "01:00PM-03:00PM", "03:00PM-06:00PM"]}]}, {"center_id": 659326, "name": "SR Pattinam APHC COVAXIN", "state_name": "Tamil Nadu", "district_name": "Sivaganga", "block_name": "kallal", "pincode": 630306, "lat": 9, "long": 78, "from": "09:00:00", "to": "18:00:00", "fee_type": "Free", "sessions": [{"session_id": "950c85e5-915a-4ef4-925c-a985ef05cc43", "date": "10-05-2021", "available_capacity": 50, "min_age_limit": 45, "vaccine": "", "slots": ["09:00AM-11:00AM", "11:00AM-01:00PM", "01:00PM-03:00PM", "03:00PM-06:00PM"]}]}, {"center_id": 640599, "name": "Vetriyur Mini Clinic", "state_name": "Tamil Nadu", "district_name": "Sivaganga", "block_name": "kallal", "pincode": 630312, "lat": 9, "long": 78, "from": "09:00:00", "to": "18:00:00", "fee_type": "Free", "sessions": [{"session_id": "628bc73e-b8f4-4127-ae91-f377d8ec3291", "date": "12-05-2021", "available_capacity": 50, "min_age_limit": 45, "vaccine": "", "slots": ["09:00AM-11:00AM", "11:00AM-01:00PM", "01:00PM-03:00PM", "03:00PM-06:00PM"]}, {"session_id": "06d7d262-78f9-4132-b444-d7c5b521b2f1", "date": "13-05-2021", "available_capacity": 50, "min_age_limit": 45, "vaccine": "", "slots": ["09:00AM-11:00AM", "11:00AM-01:00PM", "01:00PM-03:00PM", "03:00PM-06:00PM"]}]}, {"center_id": 682575, "name": "Vetriyur Mini Clinic Covaxin", "state_name": "Tamil Nadu", "district_name": "Sivaganga", "block_name": "kallal", "pincode": 630301, "lat": 0, "long": 0, "from": "09:00:00", "to": "18:00:00", "fee_type": "Free", "sessions": [{"session_id": "87cb75e4-a50a-4cb4-a3ba-2977a2b36077", "date": "12-05-2021", "available_capacity": 50, "min_age_limit": 45, "vaccine": "", "slots": ["09:00AM-11:00AM", "11:00AM-01:00PM", "01:00PM-03:00PM", "03:00PM-06:00PM"]}, {"session_id": "f85dd068-b2f5-4a73-858a-f287122d42b5", "date": "13-05-2021", "available_capacity": 50, "min_age_limit": 45, "vaccine": "", "slots": ["09:00AM-11:00AM", "11:00AM-01:00PM", "01:00PM-03:00PM", "03:00PM-06:00PM"]}]}, {"center_id": 559518, "name": "SR Pattinam APHC", "state_name": "Tamil Nadu", "district_name": "Sivaganga", "block_name": "kallal", "pincode": 630306, "lat": 9, "long": 78, "from": "09:00:00", "to": "18:00:00", "fee_type": "Free", "sessions": [{"session_id": "61c40556-1d9f-493e-946d-a4ac635d920d", "date": "12-05-2021", "available_capacity": 50, "min_age_limit": 45, "vaccine": "", "slots": ["09:00AM-11:00AM", "11:00AM-01:00PM", "01:00PM-03:00PM", "03:00PM-06:00PM"]}]}, {"center_id": 666585, "name": "Thanjakoor APHC", "state_name": "Tamil Nadu", "district_name": "Sivaganga", "block_name": "Manamadurai", "pincode": 630311, "lat": 0, "long": 0, "from": "09:00:00", "to": "18:00:00", "fee_type": "Free", "sessions": [{"session_id": "554f6e2f-a6d3-4fb6-8b04-c7cea6b7afe1", "date": "13-05-2021", "available_capacity": 50, "min_age_limit": 45, "vaccine": "", "slots": ["09:00AM-11:00AM", "11:00AM-01:00PM", "01:00PM-03:00PM", "03:00PM-06:00PM"]}]}]