[{"center_id": 601113, "name": "P K PATHAK MEMORIAL HOSPITAL", "state_name": "Jharkhand", "district_name": "Pakur", "block_name": "Pakur Sadar", "pincode": 816107, "lat": 24, "long": 87, "from": "09:00:00", "to": "18:00:00", "fee_type": "Paid", "sessions": [{"session_id": "aea56ea1-d44a-4216-ac5d-41f9fc5e3bce", "date": "30-04-2021", "available_capacity": 100, "min_age_limit": 45, "vaccine": "COVISHIELD", "slots": ["09:00AM-11:00AM", "11:00AM-01:00PM", "01:00PM-03:00PM", "03:00PM-06:00PM"]}], "vaccine_fees": [{"vaccine": "COVISHIELD", "fee": "0"}]}]