[{"center_id": 485322, "name": "Chavand Covishield", "state_name": "Gujarat", "district_name": "Amreli", "block_name": "lathi", "pincode": 365435, "lat": 21, "long": 71, "from": "09:00:00", "to": "18:00:00", "fee_type": "", "sessions": [{"session_id": "121852c3-8780-404a-a1a7-59bbf27929a8", "date": "06-05-2021", "available_capacity": 200, "min_age_limit": 45, "vaccine": "COVISHIELD", "slots": ["09:00AM-11:00AM", "11:00AM-01:00PM", "01:00PM-03:00PM", "03:00PM-06:00PM"]}, {"session_id": "5bb5eb33-26dd-4258-8cbe-bfb3bb40aa3f", "date": "07-05-2021", "available_capacity": 200, "min_age_limit": 45, "vaccine": "COVISHIELD", "slots": ["09:00AM-11:00AM", "11:00AM-01:00PM", "01:00PM-03:00PM", "03:00PM-06:00PM"]}, {"session_id": "5d400dbc-a9b6-4f6f-a91f-5b002840f613", "date": "08-05-2021", "available_capacity": 200, "min_age_limit": 45, "vaccine": "COVISHIELD", "slots": ["09:00AM-11:00AM", "11:00AM-01:00PM", "01:00PM-03:00PM", "03:00PM-06:00PM"]}, {"session_id": "fab7e6e7-8236-49d4-bcba-c7f21c4e00e9", "date": "09-05-2021", "available_capacity": 200, "min_age_limit": 45, "vaccine": "COVISHIELD", "slots": ["09:00AM-11:00AM", "11:00AM-01:00PM", "01:00PM-03:00PM", "03:00PM-06:00PM"]}, {"session_id": "d259ccbf-409c-42ec-8a12-5759b7daee05", "date": "10-05-2021", "available_capacity": 200, "min_age_limit": 45, "vaccine": "COVISHIELD", "slots": ["09:00AM-11:00AM", "11:00AM-01:00PM", "01:00PM-03:00PM", "03:00PM-06:00PM"]}], "vaccine_fees": [{"vaccine": "COVISHIELD", "fee": "0"}]}, {"center_id": 528170, "name": "Matirala Covaxin", "state_name": "Gujarat", "district_name": "Amreli", "block_name": "lathi", "pincode": 365430, "lat": 21, "long": 71, "from": "09:00:00", "to": "18:00:00", "fee_type": "", "sessions": [{"session_id": "65adbe78-6a23-4684-8bc9-64413fa14cc6", "date": "06-05-2021", "available_capacity": 200, "min_age_limit": 45, "vaccine": "COVAXIN", "slots": ["09:00AM-11:00AM", "11:00AM-01:00PM", "01:00PM-03:00PM", "03:00PM-06:00PM"]}], "vaccine_fees": [{"vaccine": "COVAXIN", "fee": "0"}]}, {"center_id": 485420, "name": "Jarkhia Covishield", "state_name": "Gujarat", "district_name": "Amreli", "block_name": "lathi", "pincode": 365430, "lat": 21, "long": 71, "from": "09:00:00", "to": "18:00:00", "fee_type": "", "sessions": [{"session_id": "aafa2a4f-c08a-4d8a-ad78-47f218b5eed4", "date": "06-05-2021", "available_capacity": 200, "min_age_limit": 45, "vaccine": "COVISHIELD", "slots": ["09:00AM-11:00AM", "11:00AM-01:00PM", "01:00PM-03:00PM", "03:00PM-06:00PM"]}, {"session_id": "e796cb2d-f37a-4cc5-b81b-85405f77cdd5", "date": "07-05-2021", "available_capacity": 200, "min_age_limit": 45, "vaccine": "COVISHIELD", "slots": ["09:00AM-11:00AM", "11:00AM-01:00PM", "01:00PM-03:00PM", "03:00PM-06:00PM"]}, {"session_id": "661d546f-3b1b-43ad-b6ad-b1a3faca08ed", "date": "08-05-2021", "available_capacity": 200, "min_age_limit": 45, "vaccine": "COVISHIELD", "slots": ["09:00AM-11:00AM", "11:00AM-01:00PM", "01:00PM-03:00PM", "03:00PM-06:00PM"]}, {"session_id": "ed5ac6c3-4b3d-45fc-8858-477d6dc342f7", "date": "09-05-2021", "available_capacity": 200, "min_age_limit": 45, "vaccine": "COVISHIELD", "slots": ["09:00AM-11:00AM", "11:00AM-01:00PM", "01:00PM-03:00PM", "03:00PM-06:00PM"]}, {"session_id": "c1000df3-29fb-47d7-9e2f-11670927aa88", "date": "10-05-2021", "available_capacity": 200, "min_age_limit": 45, "vaccine": "COVISHIELD", "slots": ["09:00AM-11:00AM", "11:00AM-01:00PM", "01:00PM-03:00PM", "03:00PM-06:00PM"]}], "vaccine_fees": [{"vaccine": "COVISHIELD", "fee": "0"}]}, {"center_id": 543945, "name": "Damnager Covisheild", "state_name": "Gujarat", "district_name": "Amreli", "block_name": "lathi", "pincode": 365430, "lat": 21, "long": 71, "from": "09:00:00", "to": "18:00:00", "fee_type": "", "sessions": [{"session_id": "1769537b-b657-4b51-9560-eae82d268e7d", "date": "06-05-2021", "available_capacity": 200, "min_age_limit": 45, "vaccine": "COVISHIELD", "slots": ["09:00AM-11:00AM", "11:00AM-01:00PM", "01:00PM-03:00PM", "03:00PM-06:00PM"]}, {"session_id": "7c02ef48-28a6-47cf-be43-d47169b17a2a", "date": "07-05-2021", "available_capacity": 200, "min_age_limit": 45, "vaccine": "COVISHIELD", "slots": ["09:00AM-11:00AM", "11:00AM-01:00PM", "01:00PM-03:00PM", "03:00PM-06:00PM"]}, {"session_id": "6fe979e6-c9a8-4eee-ab64-733b218c4cad", "date": "08-05-2021", "available_capacity": 200, "min_age_limit": 45, "vaccine": "COVISHIELD", "slots": ["09:00AM-11:00AM", "11:00AM-01:00PM", "01:00PM-03:00PM", "03:00PM-06:00PM"]}, {"session_id": "b146f533-af3e-40d8-9812-a5d13bb0ad25", "date": "09-05-2021", "available_capacity": 200, "min_age_limit": 45, "vaccine": "COVISHIELD", "slots": ["09:00AM-11:00AM", "11:00AM-01:00PM", "01:00PM-03:00PM", "03:00PM-06:00PM"]}, {"session_id": "d087f0c1-df41-49ce-8dba-a6f39bc871f1", "date": "10-05-2021", "available_capacity": 200, "min_age_limit": 45, "vaccine": "COVISHIELD", "slots": ["09:00AM-11:00AM", "11:00AM-01:00PM", "01:00PM-03:00PM", "03:00PM-06:00PM"]}], "vaccine_fees": [{"vaccine": "COVISHIELD", "fee": "0"}]}]